Workbook

Sheet Company list 1
A1: [Client] target/buyer name
A2: Exchange rate as on date | B2: X
A3: =COUNTA(A7:A1048576) -> 70
A6: Company Name | B6: HQ | C6: Initial email | D6: Status | E6: Type | F6: Rationale | G6: Revenue from source | H6: Rev (INR Cr) | I6: Headcount | J6: Website link | K6: Contact Name | L6: Designation | M6: Email Id | N6: Linkedin | O6: Relevant Investments | P6: Bucket | Q6: Previous contact
A7: Mandala Capital | B7: Mauritius | C7: 46160 | D7: Got response | E7: PE | F7: Food and agriculture focused | H7: =IFERROR((G7*1000000*$B$2)/10000000,0) -> 0 | J7: https://mandala-capital.com/ | K7: Aditya Mody | L7: Managing Director | M7: amody@mandala-capital.com | N7: https://www.linkedin.com/in/modyaditya/ | O7: Godavari Biorefineries | P7: Direct | Q7: No
A8: JM Financial | B8: Mumbai | C8: 46160 | D8: Got response | E8: PE | F8: Growth Fund III focus on agri allied businesses | H8: =IFERROR((G8*1000000*$B$2)/10000000,0) -> 0 | J8: https://jmfpe.com/JMFinancialIndiaFund | K8: Vinit Rai | L8: Managing Director | M8: vinit.rai@jmfl.com | N8: https://www.linkedin.com/in/raivinit/ | O8: Bighaat Agro | P8: Direct | Q8: Yes
A9: Catamaran Ventures | B9: Bangalore | C9: 46160 | D9: Got response | E9: FO | F9: Narayana Murthy family investment office | H9: =IFERROR((G9*1000000*$B$2)/10000000,0) -> 0 | J9: https://catamaran.in/ | K9: Sheetal Unadkat Bhat | L9: Head of PE | M9: sheetal@catamaran.in | N9: https://www.linkedin.com/in/sheetal-unadkat-bhat-26a49111/ | O9: Akshayakalpa | P9: Direct | Q9: No
A10: Convergent Finance | B10: Mumbai | C10: 46160 | D10: Got response | E10: PE | F10: Food and agriculture sector investments | H10: =IFERROR((G10*1000000*$B$2)/10000000,0) -> 0 | J10: https://convergentfinance.com/ | K10: Harsha Raghavan | L10: Managing Partner | M10: harsha@convergentfinance.com | N10: https://www.linkedin.com/in/harsha-raghavan-1218a11b5/ | O10: Hindustan Foods Limited | P10: Direct | Q10: Yes
A11: Sharrp Ventures | B11: Mumbai | C11: 46160 | D11: 46188 | E11: FO | F11: Harsh Mariwala family investment office | H11: =IFERROR((G11*1000000*$B$2)/10000000,0) -> 0 | J11: https://www.sharrpventures.com/ | K11: Divya Gupta | L11: Principal | M11: divya.gupta@sharrpventures.com | N11: https://www.linkedin.com/in/divya-gupta-5b2a5814/ | O11: Parsons Nutritionals | P11: Direct | Q11: No
A12: DS Group | B12: Noida | C12: 46160 | D12: 46188 | E12: FO | F12: Dharampal Satyapal family investment office | H12: =IFERROR((G12*1000000*$B$2)/10000000,0) -> 0 | J12: https://www.dsgroup.com/ | K12: Kunal Bhanot | L12: N/A | M12: kunal.bhanot@dsgroup.com | N12: https://www.linkedin.com/in/kunal-bhanot-5273b139/ | O12: Agri | P12: Secondary | Q12: No
A13: RP Sanjiv Goenka Family Office | B13: Kolkata | C13: 46160 | D13: Got response | E13: FO | F13: Sanjiv Goenka family investment office | H13: =IFERROR((G13*1000000*$B$2)/10000000,0) -> 0 | J13: https://www.rpsg.in/ | K13: Anshumaan Khetawat | L13: N/A | M13: anshumaan.khetawat@rpsg.in | N13: https://www.linkedin.com/in/akhetawat/ | O13: Harrisons Malyalam Limited | P13: Direct | Q13: No
A14: Negen Capital | B14: Mumbai | C14: 46160 | D14: 46188 | E14: PMS | F14: Negen Investment Trust - Category III Alternative Investment Fund | H14: =IFERROR((G14*1000000*$B$2)/10000000,0) -> 0 | J14: https://www.negencat3.com/ | K14: Jigar Shah | L14: Director | M14: jigar@negencapital.com | N14: https://www.linkedin.com/in/jigar-shah-88a44b10/ | O14: N/A | P14: Secondary | Q14: No
A15: Lighthouse Funds | B15: Mumbai | C15: 46160 | D15: 46188 | E15: PE | F15: $25-100m cheque size | H15: =IFERROR((G15*1000000*$B$2)/10000000,0) -> 0 | J15: https://www.lhfunds.com/ | K15: Vivek Kumar | L15: Principal | M15: vivek@lhfunds.com | N15: https://www.linkedin.com/in/vivek-kumar-8ab93717/ | O15: Parsons Nutritionals | P15: Direct | Q15: No
A16: Carpediem Capital | B16: Mumbai | C16: 46160 | D16: Got response | E16: PE | F16: Invests in consumer and B2B brands | H16: =IFERROR((G16*1000000*$B$2)/10000000,0) -> 0 | J16: https://carpediem-capital.com/ | K16: Tejas Gupte | L16: Vice President | M16: tejas@carpediem-capital.com | N16: https://www.linkedin.com/in/tejas-gupte-57278698/ | O16: Trufrost & Butler | P16: Direct | Q16: No
A17: Narotam Sekhsaria Family Office | B17: Mumbai | C17: 46160 | D17: Got response | E17: FO | F17: Narotam Sekhsaria family investment office | H17: =IFERROR((G17*1000000*$B$2)/10000000,0) -> 0 | J17: https://www.sekhsaria.com/index.html | K17: Pankil Shah | L17: Investment Professional | M17: pankil@sekhsaria.com | N17: https://www.linkedin.com/in/pankil-shah-21b5194/ | O17: Satyanarayan Sekhsaria Private Limited | P17: Direct | Q17: No
A18: Anicut Capital | B18: Chennai | C18: Priya Mam reach out | D18: Priya Mam reach out | E18: PE/PC | F18: Invests in B2B and consumer brands | H18: =IFERROR((G18*1000000*$B$2)/10000000,0) -> 0 | J18: https://www.anicutcapital.com/ | O18: Khetika | P18: Direct | Q18: Yes
A19: Lok Capital | B19: Mumbai | C19: 46160 | D19: 46188 | E19: PE | F19: Invests in food and agriculture | H19: =IFERROR((G19*1000000*$B$2)/10000000,0) -> 0 | J19: https://www.lokcapital.com/ | K19: Sayyam Jain | L19: Investment Associate | M19: sayyam@lokcapital.com | N19: https://www.linkedin.com/in/sayyamvjain/ | O19: Siddhi Vinayak Agri Processing Pvt Ltd | P19: Direct | Q19: No
A20: Peepul Capital Advisors | B20: Chennai | C20: Priya Mam reach out | D20: Priya Mam reach out | E20: PE | F20: Invests in the consumer sector | H20: =IFERROR((G20*1000000*$B$2)/10000000,0) -> 0 | J20: https://www.peepulcapital.com/ | O20: Innovative Foods Ltd. | P20: Direct | Q20: No
A21: SN Damani | B21: Chennai | C21: Priya Mam reach out | D21: Priya Mam reach out | E21: Strategic | F21: Invests in food producers | H21: =IFERROR((G21*1000000*$B$2)/10000000,0) -> 0 | J21: https://www.sndamani.com/ | O21: Eeki | P21: Direct | Q21: No
A22: MGA Ventures | B22: Mumbai | C22: 46163 | D22: Got response | E22: FO | F22: Ashra family investment office | J22: https://www.mgaventures.in/ | K22: Hardiki Shah | L22: Investment Analyst | M22: hardikishah@mgaventures.in | N22: https://www.linkedin.com/in/hardikis/ | O22: Kan Biosys | P22: Secondary | Q22: No
A23: Menterra | B23: Bangalore | C23: 46163 | D23: 46191 | E23: PE/VC | F23: Invests in early stage companies/agri sector | H23: =IFERROR((G23*1000000*$B$2)/10000000,0) -> 0 | J23: https://www.menterra.com/ | K23: Mukesh Sharma | L23: CIO/Co-Founder | M23: mukesh@menterra.com | N23: https://www.linkedin.com/in/mukesh-sharma-ca-cfa-9b09475/ | O23: Farm Folks | P23: Direct | Q23: No
A24: C4D Partners | B24: Bangalore | C24: Bounced | D24: Bounced | E24: PE | F24: Has a separate fund investing in India (C4D Bharat Shubharambh Fund) | H24: =IFERROR((G24*1000000*$B$2)/10000000,0) -> 0 | J24: https://c4dpartners.com/ | K24: Arvind Agarwal | L24: CEO/Founder | M24: investments@c4dpartners.com | N24: https://www.linkedin.com/in/arvind-agarwal-in/ | O24: Aliet Green | P24: Direct | Q24: No
A25: Acumen | B25: USA | C25: 46163 | D25: Got response | E25: PE | F25: Invests in Indian agri companies | H25: =IFERROR((G25*1000000*$B$2)/10000000,0) -> 0 | J25: https://acumen.org/ | K25: Nidhisha Philip | L25: Manager | M25: nphilip@acumen.org | N25: https://www.linkedin.com/in/nidhisha-philip/ | O25: Kumaon Tea | P25: Secondary | Q25: No
A26: Aavishkaar Capital | B26: Mumbai | C26: 46163 | D26: 46191 | E26: PE/VC | F26: Invests in Indian agri companies; ticket size between $5-25m | H26: =IFERROR((G26*1000000*$B$2)/10000000,0) -> 0 | J26: https://aavishkaarcapital.in/ | K26: Harsh Kherajani | L26: Investment Professional | M26: harsh@aavishkaar.in | N26: https://www.linkedin.com/in/harsh-kherajani-461b01185/ | O26: Horizon Group | P26: Direct | Q26: No
A27: 8F Asset Management | B27: Singapore | C27: 46163 | D27: 46191 | E27: PE | F27: Invests in agri/acqua companies | H27: =IFERROR((G27*1000000*$B$2)/10000000,0) -> 0 | J27: https://8f-am.com/ | K27: N/A | L27: N/A | M27: contact@8f-am.com | N27: https://www.linkedin.com/company/8f-asset-management-pte-ltd/ | O27: N/A | P27: Secondary | Q27: No
A28: Ocean14 Capital | B28: UK | C28: 46163 | D28: 46191 | E28: PE/VC | F28: Invests in acqua companies with some Indian investments | H28: =IFERROR((G28*1000000*$B$2)/10000000,0) -> 0 | J28: https://ocean14capital.com/ | K28: Ricardo Cires | L28: Portfolio and Investments | M28: ricardo.cires@ocean14capital.com | N28: https://www.linkedin.com/in/ricardo-cires-a5348535/ | O28: N/A | P28: Secondary | Q28: No
A29: Proterra | B29: USA | C29: 46163 | D29: Got response | E29: PE | F29: Invests in Asian food production and processing brands | H29: =IFERROR((G29*1000000*$B$2)/10000000,0) -> 0 | J29: https://www.proterrapartners.com/ | K29: Eduardo Barros | L29: Director | M29: ebarros@proterrapartners.com | N29: https://www.linkedin.com/in/eduardo-barros-87606b17/ | O29: N/A | P29: Secondary | Q29: No
A30: responsAbility | B30: Switzerland | C30: 46163 | D30: 46191 | E30: PE | F30: Invests in Indian food and agri producers | H30: =IFERROR((G30*1000000*$B$2)/10000000,0) -> 0 | J30: https://www.responsability.com/ | K30: Akshay Dua | L30: Head of PE | M30: akshay.dua@responsability.com | N30: https://www.linkedin.com/in/akshay-dua-3626382/ | O30: Ace International | P30: Direct | Q30: No
A31: Seviora | B31: Singapore | C31: 46163 | D31: Got response | E31: PE | F31: Invests with an Asia focus with AM holding companies (Temasek holding) | H31: =IFERROR((G31*1000000*$B$2)/10000000,0) -> 0 | J31: https://www.sevioragroup.com/ | K31: Jeremy P. | L31: Investments | M31: jeremy.phua@sevioracapital.com | N31: https://www.linkedin.com/in/jeremyphua/ | O31: N/A | P31: Secondary | Q31: No
A32: Blue Earth Capital | B32: Switzerland | C32: 46163 | D32: 46191 | E32: PE/VC | F32: Invests in Indian agri companies | H32: =IFERROR((G32*1000000*$B$2)/10000000,0) -> 0 | J32: https://blueearth.capital/ | K32: Espen Haugen | L32: Investor | M32: espenugland.haugen@blueearth.capital | N32: https://www.linkedin.com/in/espen-ugland-haugen/ | O32: Captain Fresh | P32: Secondary | Q32: No
A33: British International Investment | B33: UK | C33: 46163 | D33: 46191 | E33: PE | F33: Invests in devoloping economies | H33: =IFERROR((G33*1000000*$B$2)/10000000,0) -> 0 | J33: https://www.bii.co.uk/en/ | K33: Vaibhav Soni | L33: Investment Executive | M33: vsoni@bii.co.uk | N33: https://www.linkedin.com/in/vaibhav-soni/ | O33: N/A | P33: Secondary | Q33: No
A34: Advent International | B34: USA | C34: 46163 | D34: 46191 | E34: PE | F34: Invests in consumer and B2B brands in India | H34: =IFERROR((G34*1000000*$B$2)/10000000,0) -> 0 | J34: https://www.adventinternational.com/ | K34: Mohammed Anjarwala | L34: Partner | M34: manjarwala@adventinternational.com | N34: https://www.linkedin.com/in/anjarwala/ | O34: DFM Foods | P34: Secondary | Q34: Yes
A35: Navis Capital Partners | B35: Malaysia | C35: 46167 | D35: 46181 | E35: PE | F35: Invests in Indian companies and food processing brands | H35: =IFERROR((G35*1000000*$B$2)/10000000,0) -> 0 | J35: https://www.naviscapital.com/ | K35: Gordon C. | L35: Operating Partner | M35: gchan@naviscapital.com | N35: https://www.linkedin.com/in/gordon-c-2118734/ | O35: Srithai | P35: Direct | Q35: Yes
A36: NAB Ventures | B36: Mumbai | C36: 46167 | D36: 46181 | E36: VC | F36: Invests in agri/food processing companies | H36: =IFERROR((G36*1000000*$B$2)/10000000,0) -> 0 | J36: https://nabventures.in/Default.aspx | K36: Vikas Bhatt | L36: Managing Director | M36: vbhatt@nabventures.com | N36: https://www.linkedin.com/in/vikas-bhatt-162bb810/ | O36: Fambo | P36: Direct | Q36: No
A37: Omnivore | B37: Mumbai | C37: 46168 | D37: 46182 | E37: VC | F37: Invests in food companies | H37: =IFERROR((G37*1000000*$B$2)/10000000,0) -> 0 | J37: https://omnivore.vc/ | K37: Reihem Roy | L37: Partner | M37: reihem@omnivore.vc | N37: https://www.linkedin.com/in/reihem/ | O37: Sid's Farm | P37: Secondary | Q37: No
A38: Evolvence Capital | B38: Mumbai | C38: 46168 | D38: 46182 | E38: PE/VC | F38: Invests in food companies | H38: =IFERROR((G38*1000000*$B$2)/10000000,0) -> 0 | J38: https://www.evolvenceequity.com/ | K38: Agrata Gupta | L38: Vice President | M38: agrata@evolvenceindia.com | N38: https://www.linkedin.com/in/agratagupta/ | O38: Captain Fresh | P38: Secondary | Q38: No
A39: Caspian Capital | B39: Hyderabad | C39: 46168 | D39: 46182 | E39: PE/VC | F39: Invests in food related companies and food processing | H39: =IFERROR((G39*1000000*$B$2)/10000000,0) -> 0 | J39: https://www.caspian.in/ | K39: Ravi Narasimham | L39: Managing Director | M39: ravinarasimham@caspian.in | N39: https://www.linkedin.com/in/ravi-narasimham/ | O39: Origo | P39: Secondary | Q39: No
A40: Ankur Capital | B40: Mumbai | C40: 46168 | D40: 46182 | E40: VC | F40: Invests in food related companies | H40: =IFERROR((G40*1000000*$B$2)/10000000,0) -> 0 | J40: https://www.ankurcapital.com/ | K40: Krishnan Neelakantan | L40: Partner | M40: krishnan@ankurcapital.com | N40: https://www.linkedin.com/in/krishnan-neelakantan-a429258/ | O40: Captain Fresh | P40: Secondary | Q40: No
A41: Rabo Investments | B41: Netherlands | C41: 46168 | D41: 46182 | E41: PE/VC | F41: Has an Indian arm | H41: =IFERROR((G41*1000000*$B$2)/10000000,0) -> 0 | J41: https://raboinvestments.com/ | K41: Pieter van der Meche | L41: Managing Director | M41: pieter.van.der.meche@rabobank.com | N41: https://www.linkedin.com/in/pvdmeche/ | O41: N/A | P41: Secondary | Q41: No
A42: Prosus Ventures | B42: Netherlands | C42: 46168 | D42: 46182 | E42: VC | F42: Invests in Indian food related companies | H42: =IFERROR((G42*1000000*$B$2)/10000000,0) -> 0 | J42: https://www.prosus.com/ | K42: Apoorve Goyal | L42: Managing Director | M42: apoorve.goyal@prosus.com | N42: https://www.linkedin.com/in/apoorve-goyal-67967797/ | O42: DeHaat | P42: Secondary | Q42: No
A43: CX Partners | B43: Delhi | C43: 46168 | D43: 46182 | E43: PE | F43: Invests in Indian food related companies | H43: =IFERROR((G43*1000000*$B$2)/10000000,0) -> 0 | J43: https://www.cxpartners.in/#main | K43: Vinayak Shenvi | L43: Partner | M43: vinayak@cxpartners.in | N43: https://www.linkedin.com/in/vinayak-shenvi-1933b0309/ | O43: N/A | P43: Secondary | Q43: No
... A45: Motilal Oswal Private Equity | B45: Mumbai | C45: 46168 | D45: 46182 | E45: PE | F45: Invests in seafood companies | H45: =IFERROR((G45*1000000*$B$2)/10000000,0) -> 0 | J45: https://www.motilaloswalgroup.com/Our-Businesses/Private-Equity | K45: Radhika Kedia | L45: Investments Team | M45: radhika.kedia@motilaloswal.com | N45: https://www.linkedin.com/in/radhika-kedia-b5107a113/ | O45: N/A | P45: Secondary | Q45: No
A46: Trunorth | B46: Mumbai | C46: 46168 | D46: Got response | E46: PE | F46: Invests in consumer good export companies | H46: =IFERROR((G46*1000000*$B$2)/10000000,0) -> 0 | J46: https://www.truenorth.co.in/ | K46: Mahinder Singh Juneja | L46: Partner | M46: maninder@truenorth.co.in | N46: https://www.linkedin.com/in/maninder-singh-juneja-35a01a13/ | O46: Sesa Care | P46: Direct | Q46: Yes
A47: Samara Capital | B47: Mumbai | C47: 46168 | D47: 46182 | E47: PE | F47: Invests in consumer brands | H47: =IFERROR((G47*1000000*$B$2)/10000000,0) -> 0 | J47: https://samaracapital.com/ | K47: Akash Agarwal | L47: PE Analyst | M47: akash.agarwal@samaracapital.com | N47: https://www.linkedin.com/in/akash-agarwal-0a1459140/ | O47: Sundrop Brands | P47: Secondary | Q47: Yes
A48: Sixth Sense | B48: Mumbai | C48: 46169 | D48: 46183 | E48: VC | F48: Invests in consumer brands | H48: =IFERROR((G48*1000000*$B$2)/10000000,0) -> 0 | J48: https://sixthsenseventures.com/ | K48: Kathan Shah | L48: Principal | M48: kathan@sixth-sense.in | N48: https://www.linkedin.com/in/shahkathan/ | O48: Pushp Brand | P48: Direct | Q48: No
A49: Kedaara | B49: Mumbai | C49: 46169 | D49: 46183 | E49: PE | F49: Invests in consumer brands | H49: =IFERROR((G49*1000000*$B$2)/10000000,0) -> 0 | J49: https://kedaara.com/ | K49: Manish Kejriwal | L49: Founder/Managing Partner | M49: manish.kejriwal@kedaara.com | N49: https://www.linkedin.com/in/manish-kejriwal-1a7336/ | O49: Dairy Day | P49: Secondary | Q49: Yes
A50: A91 Partners | B50: Mumbai | C50: 46169 | D50: 46183 | E50: PE | F50: Invests in consumer brands | H50: =IFERROR((G50*1000000*$B$2)/10000000,0) -> 0 | J50: https://a91partners.com/ | K50: Prajesh Dawda | L50: AVP | M50: prajesh@a91partners.com | N50: https://www.linkedin.com/in/prajesh-dawda-284b4297/ | O50: Pushp Brand | P50: Direct | Q50: No
A51: Chrys Capital | B51: Mauritius | C51: 46169 | D51: 46183 | E51: PE | F51: Invests in consumer brands | H51: =IFERROR((G51*1000000*$B$2)/10000000,0) -> 0 | J51: https://chryscapital.com/ | K51: Connel Coelho | L51: Vice President | M51: connel@chryscapital.com | N51: https://www.linkedin.com/in/connel-coelho-cfa-79974043/ | O51: Theobroma | P51: Secondary | Q51: No
A52: Everstone Capital | B52: Mumbai | C52: 46169 | D52: 46183 | E52: PE | F52: Invests in consumer brands | H52: =IFERROR((G52*1000000*$B$2)/10000000,0) -> 0 | J52: https://everstonecapital.com/ | K52: Ronak Fatnani | L52: Investment Professional | M52: rfatnani@everstonecapital.com | N52: https://www.linkedin.com/in/ronak-fatnani-613477189/ | O52: Burger King | P52: Secondary | Q52: No
A53: Faering Capital | B53: Mumbai | C53: 46169 | D53: Got response | E53: PE | F53: Invests in packaged food and related | H53: =IFERROR((G53*1000000*$B$2)/10000000,0) -> 0 | J53: https://www.faeringcapital.com/index | K53: Shyam Patwari | L53: Director | M53: shyam@faeringcapital.com | N53: https://www.linkedin.com/in/shyampatwari/ | O53: Prataap Snacks | P53: Secondary | Q53: No
A54: Lightrock | B54: UK | C54: 46169 | D54: 46183 | E54: PE | F54: Invests in food processing and related companies | H54: =IFERROR((G54*1000000*$B$2)/10000000,0) -> 0 | J54: https://www.lightrock.com/ | K54: Ankit Solanki | L54: Investment Associate | M54: ankit@lightrock.com | N54: https://www.linkedin.com/in/ankit-solanki-599801138/ | O54: Waycool | P54: Direct | Q54: No
A55: Gulf Capital | B55: Abu Dhabi | C55: 46169 | D55: 46183 | E55: PE | F55: Invests in food processing and Indian brands | H55: =IFERROR((G55*1000000*$B$2)/10000000,0) -> 0 | J55: https://www.gulfcapital.com/ | K55: Mohammad Madani | L55: Managing Director | M55: mmadani@gulfcapital.com | N55: https://www.linkedin.com/in/mohammad-madani-2a47bb9/ | O55: CHO Company | P55: Direct | Q55: Yes
A56: Daiwa PI Partners | B56: Japan | C56: 46169 | D56: 46183 | E56: PE | F56: Invests in agri companies and India | H56: =IFERROR((G56*1000000*$B$2)/10000000,0) -> 0 | J56: https://www.dpipartners.co.jp/en/ | K56: Abhinav Goswami | L56: Senior Director | M56: abhinav.goswami@daiwapipsg.com | N56: https://www.linkedin.com/in/abhigoswami/ | O56: Marine Pro Foods | P56: Direct | Q56: No
A57: Saint Capital Fund | B57: Mauritius | C57: 46170 | D57: 46184 | E57: PE | F57: Invests in Indian agri companies | H57: =IFERROR((G57*1000000*$B$2)/10000000,0) -> 0 | J57: https://www.saintcapitalfund.com/ | K57: Mayank Agarwal | L57: Director | M57: mayank@saintcapitalfund.com | N57: https://www.linkedin.com/in/mayank-agrawal-606514314/ | O57: Kn Agri Resources Limited | P57: Secondary | Q57: No
A58: Alteria Capital | B58: Mumbai | C58: 46170 | D58: 46184 | E58: VC | F58: Invests in agri companies | H58: =IFERROR((G58*1000000*$B$2)/10000000,0) -> 0 | J58: https://alteriacapital.com/ | K58: Yash Jain | L58: Senior VP | M58: yash@alteriacapital.com | N58: https://www.linkedin.com/in/yash-jain-260946a7/ | O58: Waycool | P58: Direct | Q58: No
A59: DSG Consumer Partners | B59: Singapore | C59: 46170 | D59: 46184 | E59: PE/VC | F59: Invests in Indian agri companies | H59: =IFERROR((G59*1000000*$B$2)/10000000,0) -> 0 | J59: https://www.dsgcp.com/?_gl=1*148wqhx*_up*MQ..*_ga*MTQ5Njk1NjI3MC4xNzc5ODc2NzY1*_ga_604EX73PD8*czE3Nzk4NzY3NjQkbzEkZzEkdDE3Nzk4NzczNjckajYwJGwwJGgw | K59: Varun Parekh | L59: Investment Professional | M59: vparekh@dsgcp.com | N59: https://www.linkedin.com/in/varun-parekh-3b84b7148/ | O59: Anveshan | P59: Direct | Q59: No
A60: Incofin Investment Management | B60: Belgium | C60: 46170 | D60: Got response | E60: PE | F60: Invests in Indian agri companies | H60: =IFERROR((G60*1000000*$B$2)/10000000,0) -> 0 | J60: https://incofin.com/ | K60: Ritesh Modi | L60: Senior Investment Manager | M60: ritesh.modi@incofin.com | N60: https://www.linkedin.com/in/modiritesh79/ | O60: N/A | P60: Secondary | Q60: No
A61: Singularity AMC | B61: Mumbai | C61: 46170 | D61: 46184 | E61: PE | F61: Invests in Indian agri companies | H61: =IFERROR((G61*1000000*$B$2)/10000000,0) -> 0 | J61: https://singularityamc.com/ | K61: Sahil Gala | L61: Vice President | M61: sahil@singularityamc.in | N61: https://www.linkedin.com/in/sahil-gala-3a271b102/ | O61: N/A | P61: Secondary | Q61: No
A62: Verlinvest | B62: Brussels | C62: 46170 | D62: 46184 | E62: PE | F62: Invests in global Indian consumer companies | H62: =IFERROR((G62*1000000*$B$2)/10000000,0) -> 0 | J62: https://www.verlinvest.com/ | K62: Krishna Chablani | L62: Investment Professional | M62: kchablani@verlinvest.asia | N62: https://www.linkedin.com/in/krishnachablani/ | O62: Mutti | P62: Secondary | Q62: No
A63: Paragon Partners | B63: Mumbai | C63: 46174 | D63: 46188 | E63: PE | F63: Invests in meat/seafood companies | H63: =IFERROR((G63*1000000*$B$2)/10000000,0) -> 0 | J63: https://www.paragonpartners.in/ | K63: Niten Lalpuria | L63: Partner | M63: niten@paragonpartners.in | N63: https://www.linkedin.com/in/nitenl/ | O63: Tendercuts | P63: Direct | Q63: No
A64: Asha Ventures | B64: Mumbai | C64: 46174 | D64: Got response | E64: PE/VC | F64: Invests in consumer companies | H64: =IFERROR((G64*1000000*$B$2)/10000000,0) -> 0 | J64: https://ashaventures.in/ | K64: Amit Mehta | L64: Managing Partner | M64: amit@ashaventures.in | N64: https://www.linkedin.com/in/amit-mehta-6b90b92/ | O64: Wonderland Foods | P64: Direct | Q64: No
A65: Gaja Capital | B65: Mumbai | C65: 46174 | D65: 46188 | E65: PE | F65: Invests in consumer companies | H65: =IFERROR((G65*1000000*$B$2)/10000000,0) -> 0 | J65: https://gajacapital.com/ | K65: Dheeraj Devata | L65: Partner | M65: dheeraj.devata@gajacapital.com | N65: https://www.linkedin.com/in/dheerajdevata/ | O65: Eggoz Nutrition | P65: Secondary | Q65: Yes
A66: TVS Capital | B66: Chennai | C66: 46174 | D66: 46188 | E66: PE | F66: Invests in consumer and food processing companies | H66: =IFERROR((G66*1000000*$B$2)/10000000,0) -> 0 | J66: https://www.tvscapital.in/ | K66: Praveen Sridharan | L66: Partner | M66: praveen.sridharan@tvscapital.in | N66: https://www.linkedin.com/in/praveen-sridharan-7623325/ | O66: Dunar Foods Limited | P66: Direct | Q66: No
A67: Premji Invest | B67: Bangalore | C67: 46174 | D67: 46188 | E67: PE | F67: Invests in consumer companies | H67: =IFERROR((G67*1000000*$B$2)/10000000,0) -> 0 | J67: https://www.premjiinvest.com/ | K67: Alisha Mittal | L67: Vice President | M67: alisha.mittal@premjiinvest.com | N67: https://www.linkedin.com/in/alisha-mittal-b7a4a4ba/ | O67: Organic India | P67: Secondary | Q67: Yes
A68: 360 One (IIFL PE) | B68: Mumbai | C68: 46174 | D68: Got response | E68: PE | F68: Invests in agri companies | H68: =IFERROR((G68*1000000*$B$2)/10000000,0) -> 0 | J68: https://www.360.one/ | K68: Anshuman Maheshwary | L68: CEO | M68: anshuman.maheshwary@iiflw.com | N68: https://www.linkedin.com/in/anshuman-maheshwary-587323/ | O68: N/A | P68: Secondary | Q68: No
A69: Multiples Equity | B69: Mumbai | C69: 46174 | D69: 46188 | E69: PE | F69: Invests in meat companies | H69: =IFERROR((G69*1000000*$B$2)/10000000,0) -> 0 | J69: https://www.multiplesequity.com/ | K69: Mehul Agarwal | L69: Vice President | M69: mehul.agarwal@multiplesequity.com | N69: https://www.linkedin.com/in/mehul-agarwal-8a231391/ | O69: Licious | P69: Yes | Q69: Yes
A70: Kotak Private Equity | B70: Mumbai | C70: 46174 | D70: Got response | E70: PE | F70: Invests in meat companies | H70: =IFERROR((G70*1000000*$B$2)/10000000,0) -> 0 | J70: https://www.kotakalternateasset.com/ | K70: Akshit Sandooja | L70: Investment Professional | M70: akshit.sandooja@kotak.com | N70: https://www.linkedin.com/in/akshitsandooja/ | O70: Licious | P70: Yes | Q70: Yes
A71: Umious | B71: Japan | C71: 46174 | D71: 46188 | E71: Strategic | F71: Invests in/acquires seafood companies | H71: =IFERROR((G71*1000000*$B$2)/10000000,0) -> 0 | J71: https://www.umios.com/en/ | K71: Lub van der Berg | L71: Director | M71: lub@seafoodconnection.nl | N71: https://www.linkedin.com/in/lubvandenberg/ | O71: Multiple | P71: Strategics | Q71: No
A72: Nissui | B72: Japan | C72: Contact not found | D72: Contact not found | E72: Strategic | F72: Invests in/acquires seafood companies | H72: =IFERROR((G72*1000000*$B$2)/10000000,0) -> 0 | J72: https://www.nissui.co.jp/english/index.html | O72: Multiple | P72: Strategics | Q72: No
A73: Aqua Spark | B73: Netherlands | C73: 46174 | D73: 46188 | E73: PE | F73: Invests in food processing and production companies | H73: =IFERROR((G73*1000000*$B$2)/10000000,0) -> 0 | J73: https://aqua-spark.nl/ | K73: Katherine Bryar | L73: Director | M73: katherine@aquna.com | N73: https://www.linkedin.com/in/katherinebryar/ | O73: Lake Harvest Group | P73: Direct | Q73: No
A74: Marubeni Consumer Platform | B74: Japan | C74: 46174 | D74: 46188 | E74: Strategic | F74: Set up a new Indian investment platform in 2026 | H74: =IFERROR((G74*1000000*$B$2)/10000000,0) -> 0 | J74: https://marubeni-cp.com/en/news/20260318.html | K74: Coco Tay | L74: Investment Professional | M74: coco-tay@marubeni-gc.com | N74: https://www.linkedin.com/in/coco-tay-b55535a1/ | O74: Multiple | P74: Secondary | Q74: No
A75: Sojitz | B75: Japan | C75: 46174 | D75: 46188 | E75: Strategic | F75: Invests in south east Asian companies | H75: =IFERROR((G75*1000000*$B$2)/10000000,0) -> 0 | J75: https://www.sojitz.com/en/ | K75: Kent K. | L75: Assistant General Manager | M75: katori.kentaro@sojitz.com | N75: https://www.linkedin.com/in/kent-k-231343/ | O75: Multiple | P75: Secondary | Q75: No
A76: Al Dahra | B76: UAE | C76: 46174 | D76: Bounced | E76: Strategic | F76: Invests in agri companoes | H76: =IFERROR((G76*1000000*$B$2)/10000000,0) -> 0 | J76: https://aldahra.com/ | K76: Tanas Stefan | L76: Senior Manager Corporate Development | M76: tanas.stefan@aldahra.com | N76: https://www.linkedin.com/in/tanas-stefan/ | O76: Multiple | P76: Secondary | Q76: No

Sheet Company list 2
A1: [Client] target/buyer name
A2: Exchange rate as on date | B2: X
A3: =COUNTA(A7:A1048576) -> 0
A6: Company Name | B6: HQ | C6: Initial email | D6: Status | E6: Rationale | F6: Revenue from source | G6: Rev (INR Cr) | H6: Headcount | I6: Website link | J6: Contact Name | K6: Designation | L6: Email Id | M6: Linkedin | N6: Regarding
G7: =IFERROR((F7*1000000*$B$2)/10000000,0) -> 0
G8: =IFERROR((F8*1000000*$B$2)/10000000,0) -> 0
G9: =IFERROR((F9*1000000*$B$2)/10000000,0) -> 0
G10: =IFERROR((F10*1000000*$B$2)/10000000,0) -> 0
G11: =IFERROR((F11*1000000*$B$2)/10000000,0) -> 0
G12: =IFERROR((F12*1000000*$B$2)/10000000,0) -> 0
G13: =IFERROR((F13*1000000*$B$2)/10000000,0) -> 0
G14: =IFERROR((F14*1000000*$B$2)/10000000,0) -> 0
G15: =IFERROR((F15*1000000*$B$2)/10000000,0) -> 0
G16: =IFERROR((F16*1000000*$B$2)/10000000,0) -> 0
G17: =IFERROR((F17*1000000*$B$2)/10000000,0) -> 0
G18: =IFERROR((F18*1000000*$B$2)/10000000,0) -> 0
... G56: =IFERROR((F56*1000000*$B$2)/10000000,0) -> 0

Sheet Company list 3
A1: [Client] target/buyer name
A2: Exchange rate as on date | B2: X
A3: =COUNTA(A7:A1048576) -> 0
A6: Company Name | B6: HQ | C6: Initial email | D6: Status | E6: Rationale | F6: Revenue from source | G6: Rev (INR Cr) | H6: Headcount | I6: Website link | J6: Contact Name | K6: Designation | L6: Email Id | M6: Linkedin | N6: Regarding
G7: =IFERROR((F7*1000000*$B$2)/10000000,0) -> 0
G8: =IFERROR((F8*1000000*$B$2)/10000000,0) -> 0
G9: =IFERROR((F9*1000000*$B$2)/10000000,0) -> 0
G10: =IFERROR((F10*1000000*$B$2)/10000000,0) -> 0
G11: =IFERROR((F11*1000000*$B$2)/10000000,0) -> 0
G12: =IFERROR((F12*1000000*$B$2)/10000000,0) -> 0
G13: =IFERROR((F13*1000000*$B$2)/10000000,0) -> 0
G14: =IFERROR((F14*1000000*$B$2)/10000000,0) -> 0
G15: =IFERROR((F15*1000000*$B$2)/10000000,0) -> 0
G16: =IFERROR((F16*1000000*$B$2)/10000000,0) -> 0
G17: =IFERROR((F17*1000000*$B$2)/10000000,0) -> 0
G18: =IFERROR((F18*1000000*$B$2)/10000000,0) -> 0
... G56: =IFERROR((F56*1000000*$B$2)/10000000,0) -> 0

Sheet Emailing schedule
A1: Next set of emails due in (days) | C1: =MIN(J7:M76) -> 3 | D1: Count | E1: =SUBTOTAL(3,A7:A1048576) -> 70
D2: Check | E2: =E1-'Company list 1'!A3-'Company list 2'!A3-'Company list 3'!A3 -> 0
B5: =IF(COUNTIF(B7:B1048576,"Error")>0,"Error", "Go") -> Go | C5: =IF(COUNTIF(C7:C1048576,"Error")>0,"Error", "Go") -> Go | E5: =IF(COUNTIF(E7:E1048576,"Error")>0,"Error", "Go") -> Go
A6: Company name | B6: Check to previous sheets | C6: Regarding | D6: Initial date | E6: Status | F6: Bi-weekly follow up | G6: Bi-weekly follow up | H6: Bi-weekly follow up | I6: Bi-weekly follow up | J6: Follow ups (in days)
A7: Mandala Capital | B7: =IFERROR(IF(COUNTIF('Company list 1'!$A$7:$A$1048576,A7)+COUNTIF('Company list 2'!$A$7:$A$1048576,A7)+COUNTIF('Company list 3'!$A$7:$A$1048576, A7)=1, "Yes", "Error"),"Error") -> Yes | D7: =_xlfn.LET(_xlpm.L,IFERROR(_xlfn.XLOOKUP(A7,#REF!,#REF!),_xlfn.XLOOKUP(A7,'Company list 1'!A:A,'Company list 1'!C:C,"")),IF(_xlpm.L=0,"",_xlpm.L)) -> 46160 | E7: =_xlfn.LET(_xlpm.d,IFERROR(_xlfn.XLOOKUP(A7,#REF!,#REF!),_xlfn.XLOOKUP(A7,'Company list 1'!A:A,'Company list 1'!D:D,"")),IF(_xlpm.d=0,"",_xlpm.d)) -> Got response | F7: =IF(ISNUMBER($E7),D7+14,"") | G7: =IF(ISNUMBER($E7),F7+14,"") | H7: =IF(ISNUMBER($E7),G7+14,"") | I7: =IF(ISNUMBER($E7),H7+14,"") | J7: =IF(NOT(ISNUMBER($E7)),"",IF($E7>=F7,"Done",F7-TODAY())) | K7: =IF(NOT(ISNUMBER($E7)),"",IF($E7>=G7,"Done",G7-TODAY())) | L7: =IF(NOT(ISNUMBER($E7)),"",IF($E7>=H7,"Done",H7-TODAY())) | M7: =IF(NOT(ISNUMBER($E7)),"",IF($E7>=I7,"Done",I7-TODAY()))
A8: JM Financial | B8: =IFERROR(IF(COUNTIF('Company list 1'!$A$7:$A$1048576,A8)+COUNTIF('Company list 2'!$A$7:$A$1048576,A8)+COUNTIF('Company list 3'!$A$7:$A$1048576, A8)=1, "Yes", "Error"),"Error") -> Yes | D8: =_xlfn.LET(_xlpm.L,IFERROR(_xlfn.XLOOKUP(A8,#REF!,#REF!),_xlfn.XLOOKUP(A8,'Company list 1'!A:A,'Company list 1'!C:C,"")),IF(_xlpm.L=0,"",_xlpm.L)) -> 46160 | E8: =_xlfn.LET(_xlpm.d,IFERROR(_xlfn.XLOOKUP(A8,#REF!,#REF!),_xlfn.XLOOKUP(A8,'Company list 1'!A:A,'Company list 1'!D:D,"")),IF(_xlpm.d=0,"",_xlpm.d)) -> Got response | F8: =IF(ISNUMBER($E8),D8+14,"") | G8: =IF(ISNUMBER($E8),F8+14,"") | H8: =IF(ISNUMBER($E8),G8+14,"") | I8: =IF(ISNUMBER($E8),H8+14,"") | J8: =IF(NOT(ISNUMBER($E8)),"",IF($E8>=F8,"Done",F8-TODAY())) | K8: =IF(NOT(ISNUMBER($E8)),"",IF($E8>=G8,"Done",G8-TODAY())) | L8: =IF(NOT(ISNUMBER($E8)),"",IF($E8>=H8,"Done",H8-TODAY())) | M8: =IF(NOT(ISNUMBER($E8)),"",IF($E8>=I8,"Done",I8-TODAY()))
A9: Catamaran Ventures | B9: =IFERROR(IF(COUNTIF('Company list 1'!$A$7:$A$1048576,A9)+COUNTIF('Company list 2'!$A$7:$A$1048576,A9)+COUNTIF('Company list 3'!$A$7:$A$1048576, A9)=1, "Yes", "Error"),"Error") -> Yes | D9: =_xlfn.LET(_xlpm.L,IFERROR(_xlfn.XLOOKUP(A9,#REF!,#REF!),_xlfn.XLOOKUP(A9,'Company list 1'!A:A,'Company list 1'!C:C,"")),IF(_xlpm.L=0,"",_xlpm.L)) -> 46160 | E9: =_xlfn.LET(_xlpm.d,IFERROR(_xlfn.XLOOKUP(A9,#REF!,#REF!),_xlfn.XLOOKUP(A9,'Company list 1'!A:A,'Company list 1'!D:D,"")),IF(_xlpm.d=0,"",_xlpm.d)) -> Got response | F9: =IF(ISNUMBER($E9),D9+14,"") | G9: =IF(ISNUMBER($E9),F9+14,"") | H9: =IF(ISNUMBER($E9),G9+14,"") | I9: =IF(ISNUMBER($E9),H9+14,"") | J9: =IF(NOT(ISNUMBER($E9)),"",IF($E9>=F9,"Done",F9-TODAY())) | K9: =IF(NOT(ISNUMBER($E9)),"",IF($E9>=G9,"Done",G9-TODAY())) | L9: =IF(NOT(ISNUMBER($E9)),"",IF($E9>=H9,"Done",H9-TODAY())) | M9: =IF(NOT(ISNUMBER($E9)),"",IF($E9>=I9,"Done",I9-TODAY()))
A10: Convergent Finance | B10: =IFERROR(IF(COUNTIF('Company list 1'!$A$7:$A$1048576,A10)+COUNTIF('Company list 2'!$A$7:$A$1048576,A10)+COUNTIF('Company list 3'!$A$7:$A$1048576, A10)=1, "Yes", "Error"),"Error") -> Yes | D10: =_xlfn.LET(_xlpm.L,IFERROR(_xlfn.XLOOKUP(A10,#REF!,#REF!),_xlfn.XLOOKUP(A10,'Company list 1'!A:A,'Company list 1'!C:C,"")),IF(_xlpm.L=0,"",_xlpm.L)) -> 46160 | E10: =_xlfn.LET(_xlpm.d,IFERROR(_xlfn.XLOOKUP(A10,#REF!,#REF!),_xlfn.XLOOKUP(A10,'Company list 1'!A:A,'Company list 1'!D:D,"")),IF(_xlpm.d=0,"",_xlpm.d)) -> Got response | F10: =IF(ISNUMBER($E10),D10+14,"") | G10: =IF(ISNUMBER($E10),F10+14,"") | H10: =IF(ISNUMBER($E10),G10+14,"") | I10: =IF(ISNUMBER($E10),H10+14,"") | J10: =IF(NOT(ISNUMBER($E10)),"",IF($E10>=F10,"Done",F10-TODAY())) | K10: =IF(NOT(ISNUMBER($E10)),"",IF($E10>=G10,"Done",G10-TODAY())) | L10: =IF(NOT(ISNUMBER($E10)),"",IF($E10>=H10,"Done",H10-TODAY())) | M10: =IF(NOT(ISNUMBER($E10)),"",IF($E10>=I10,"Done",I10-TODAY()))
A11: Sharrp Ventures | B11: =IFERROR(IF(COUNTIF('Company list 1'!$A$7:$A$1048576,A11)+COUNTIF('Company list 2'!$A$7:$A$1048576,A11)+COUNTIF('Company list 3'!$A$7:$A$1048576, A11)=1, "Yes", "Error"),"Error") -> Yes | D11: =_xlfn.LET(_xlpm.L,IFERROR(_xlfn.XLOOKUP(A11,#REF!,#REF!),_xlfn.XLOOKUP(A11,'Company list 1'!A:A,'Company list 1'!C:C,"")),IF(_xlpm.L=0,"",_xlpm.L)) -> 46160 | E11: =_xlfn.LET(_xlpm.d,IFERROR(_xlfn.XLOOKUP(A11,#REF!,#REF!),_xlfn.XLOOKUP(A11,'Company list 1'!A:A,'Company list 1'!D:D,"")),IF(_xlpm.d=0,"",_xlpm.d)) -> 46188 | F11: =IF(ISNUMBER($E11),D11+14,"") -> 46174 | G11: =IF(ISNUMBER($E11),F11+14,"") -> 46188 | H11: =IF(ISNUMBER($E11),G11+14,"") -> 46202 | I11: =IF(ISNUMBER($E11),H11+14,"") -> 46216 | J11: =IF(NOT(ISNUMBER($E11)),"",IF($E11>=F11,"Done",F11-TODAY())) -> Done | K11: =IF(NOT(ISNUMBER($E11)),"",IF($E11>=G11,"Done",G11-TODAY())) -> Done | L11: =IF(NOT(ISNUMBER($E11)),"",IF($E11>=H11,"Done",H11-TODAY())) -> 10 | M11: =IF(NOT(ISNUMBER($E11)),"",IF($E11>=I11,"Done",I11-TODAY())) -> 24
A12: DS Group | B12: =IFERROR(IF(COUNTIF('Company list 1'!$A$7:$A$1048576,A12)+COUNTIF('Company list 2'!$A$7:$A$1048576,A12)+COUNTIF('Company list 3'!$A$7:$A$1048576, A12)=1, "Yes", "Error"),"Error") -> Yes | D12: =_xlfn.LET(_xlpm.L,IFERROR(_xlfn.XLOOKUP(A12,#REF!,#REF!),_xlfn.XLOOKUP(A12,'Company list 1'!A:A,'Company list 1'!C:C,"")),IF(_xlpm.L=0,"",_xlpm.L)) -> 46160 | E12: =_xlfn.LET(_xlpm.d,IFERROR(_xlfn.XLOOKUP(A12,#REF!,#REF!),_xlfn.XLOOKUP(A12,'Company list 1'!A:A,'Company list 1'!D:D,"")),IF(_xlpm.d=0,"",_xlpm.d)) -> 46188 | F12: =IF(ISNUMBER($E12),D12+14,"") -> 46174 | G12: =IF(ISNUMBER($E12),F12+14,"") -> 46188 | H12: =IF(ISNUMBER($E12),G12+14,"") -> 46202 | I12: =IF(ISNUMBER($E12),H12+14,"") -> 46216 | J12: =IF(NOT(ISNUMBER($E12)),"",IF($E12>=F12,"Done",F12-TODAY())) -> Done | K12: =IF(NOT(ISNUMBER($E12)),"",IF($E12>=G12,"Done",G12-TODAY())) -> Done | L12: =IF(NOT(ISNUMBER($E12)),"",IF($E12>=H12,"Done",H12-TODAY())) -> 10 | M12: =IF(NOT(ISNUMBER($E12)),"",IF($E12>=I12,"Done",I12-TODAY())) -> 24
A13: RP Sanjiv Goenka Family Office | B13: =IFERROR(IF(COUNTIF('Company list 1'!$A$7:$A$1048576,A13)+COUNTIF('Company list 2'!$A$7:$A$1048576,A13)+COUNTIF('Company list 3'!$A$7:$A$1048576, A13)=1, "Yes", "Error"),"Error") -> Yes | D13: =_xlfn.LET(_xlpm.L,IFERROR(_xlfn.XLOOKUP(A13,#REF!,#REF!),_xlfn.XLOOKUP(A13,'Company list 1'!A:A,'Company list 1'!C:C,"")),IF(_xlpm.L=0,"",_xlpm.L)) -> 46160 | E13: =_xlfn.LET(_xlpm.d,IFERROR(_xlfn.XLOOKUP(A13,#REF!,#REF!),_xlfn.XLOOKUP(A13,'Company list 1'!A:A,'Company list 1'!D:D,"")),IF(_xlpm.d=0,"",_xlpm.d)) -> Got response | F13: =IF(ISNUMBER($E13),D13+14,"") | G13: =IF(ISNUMBER($E13),F13+14,"") | H13: =IF(ISNUMBER($E13),G13+14,"") | I13: =IF(ISNUMBER($E13),H13+14,"") | J13: =IF(NOT(ISNUMBER($E13)),"",IF($E13>=F13,"Done",F13-TODAY())) | K13: =IF(NOT(ISNUMBER($E13)),"",IF($E13>=G13,"Done",G13-TODAY())) | L13: =IF(NOT(ISNUMBER($E13)),"",IF($E13>=H13,"Done",H13-TODAY())) | M13: =IF(NOT(ISNUMBER($E13)),"",IF($E13>=I13,"Done",I13-TODAY()))
A14: Negen Capital | B14: =IFERROR(IF(COUNTIF('Company list 1'!$A$7:$A$1048576,A14)+COUNTIF('Company list 2'!$A$7:$A$1048576,A14)+COUNTIF('Company list 3'!$A$7:$A$1048576, A14)=1, "Yes", "Error"),"Error") -> Yes | D14: =_xlfn.LET(_xlpm.L,IFERROR(_xlfn.XLOOKUP(A14,#REF!,#REF!),_xlfn.XLOOKUP(A14,'Company list 1'!A:A,'Company list 1'!C:C,"")),IF(_xlpm.L=0,"",_xlpm.L)) -> 46160 | E14: =_xlfn.LET(_xlpm.d,IFERROR(_xlfn.XLOOKUP(A14,#REF!,#REF!),_xlfn.XLOOKUP(A14,'Company list 1'!A:A,'Company list 1'!D:D,"")),IF(_xlpm.d=0,"",_xlpm.d)) -> 46188 | F14: =IF(ISNUMBER($E14),D14+14,"") -> 46174 | G14: =IF(ISNUMBER($E14),F14+14,"") -> 46188 | H14: =IF(ISNUMBER($E14),G14+14,"") -> 46202 | I14: =IF(ISNUMBER($E14),H14+14,"") -> 46216 | J14: =IF(NOT(ISNUMBER($E14)),"",IF($E14>=F14,"Done",F14-TODAY())) -> Done | K14: =IF(NOT(ISNUMBER($E14)),"",IF($E14>=G14,"Done",G14-TODAY())) -> Done | L14: =IF(NOT(ISNUMBER($E14)),"",IF($E14>=H14,"Done",H14-TODAY())) -> 10 | M14: =IF(NOT(ISNUMBER($E14)),"",IF($E14>=I14,"Done",I14-TODAY())) -> 24
A15: Lighthouse Funds | B15: =IFERROR(IF(COUNTIF('Company list 1'!$A$7:$A$1048576,A15)+COUNTIF('Company list 2'!$A$7:$A$1048576,A15)+COUNTIF('Company list 3'!$A$7:$A$1048576, A15)=1, "Yes", "Error"),"Error") -> Yes | D15: =_xlfn.LET(_xlpm.L,IFERROR(_xlfn.XLOOKUP(A15,#REF!,#REF!),_xlfn.XLOOKUP(A15,'Company list 1'!A:A,'Company list 1'!C:C,"")),IF(_xlpm.L=0,"",_xlpm.L)) -> 46160 | E15: =_xlfn.LET(_xlpm.d,IFERROR(_xlfn.XLOOKUP(A15,#REF!,#REF!),_xlfn.XLOOKUP(A15,'Company list 1'!A:A,'Company list 1'!D:D,"")),IF(_xlpm.d=0,"",_xlpm.d)) -> 46188 | F15: =IF(ISNUMBER($E15),D15+14,"") -> 46174 | G15: =IF(ISNUMBER($E15),F15+14,"") -> 46188 | H15: =IF(ISNUMBER($E15),G15+14,"") -> 46202 | I15: =IF(ISNUMBER($E15),H15+14,"") -> 46216 | J15: =IF(NOT(ISNUMBER($E15)),"",IF($E15>=F15,"Done",F15-TODAY())) -> Done | K15: =IF(NOT(ISNUMBER($E15)),"",IF($E15>=G15,"Done",G15-TODAY())) -> Done | L15: =IF(NOT(ISNUMBER($E15)),"",IF($E15>=H15,"Done",H15-TODAY())) -> 10 | M15: =IF(NOT(ISNUMBER($E15)),"",IF($E15>=I15,"Done",I15-TODAY())) -> 24
A16: Carpediem Capital | B16: =IFERROR(IF(COUNTIF('Company list 1'!$A$7:$A$1048576,A16)+COUNTIF('Company list 2'!$A$7:$A$1048576,A16)+COUNTIF('Company list 3'!$A$7:$A$1048576, A16)=1, "Yes", "Error"),"Error") -> Yes | D16: =_xlfn.LET(_xlpm.L,IFERROR(_xlfn.XLOOKUP(A16,#REF!,#REF!),_xlfn.XLOOKUP(A16,'Company list 1'!A:A,'Company list 1'!C:C,"")),IF(_xlpm.L=0,"",_xlpm.L)) -> 46160 | E16: =_xlfn.LET(_xlpm.d,IFERROR(_xlfn.XLOOKUP(A16,#REF!,#REF!),_xlfn.XLOOKUP(A16,'Company list 1'!A:A,'Company list 1'!D:D,"")),IF(_xlpm.d=0,"",_xlpm.d)) -> Got response | F16: =IF(ISNUMBER($E16),D16+14,"") | G16: =IF(ISNUMBER($E16),F16+14,"") | H16: =IF(ISNUMBER($E16),G16+14,"") | I16: =IF(ISNUMBER($E16),H16+14,"") | J16: =IF(NOT(ISNUMBER($E16)),"",IF($E16>=F16,"Done",F16-TODAY())) | K16: =IF(NOT(ISNUMBER($E16)),"",IF($E16>=G16,"Done",G16-TODAY())) | L16: =IF(NOT(ISNUMBER($E16)),"",IF($E16>=H16,"Done",H16-TODAY())) | M16: =IF(NOT(ISNUMBER($E16)),"",IF($E16>=I16,"Done",I16-TODAY()))
A17: Narotam Sekhsaria Family Office | B17: =IFERROR(IF(COUNTIF('Company list 1'!$A$7:$A$1048576,A17)+COUNTIF('Company list 2'!$A$7:$A$1048576,A17)+COUNTIF('Company list 3'!$A$7:$A$1048576, A17)=1, "Yes", "Error"),"Error") -> Yes | D17: =_xlfn.LET(_xlpm.L,IFERROR(_xlfn.XLOOKUP(A17,#REF!,#REF!),_xlfn.XLOOKUP(A17,'Company list 1'!A:A,'Company list 1'!C:C,"")),IF(_xlpm.L=0,"",_xlpm.L)) -> 46160 | E17: =_xlfn.LET(_xlpm.d,IFERROR(_xlfn.XLOOKUP(A17,#REF!,#REF!),_xlfn.XLOOKUP(A17,'Company list 1'!A:A,'Company list 1'!D:D,"")),IF(_xlpm.d=0,"",_xlpm.d)) -> Got response | F17: =IF(ISNUMBER($E17),D17+14,"") | G17: =IF(ISNUMBER($E17),F17+14,"") | H17: =IF(ISNUMBER($E17),G17+14,"") | I17: =IF(ISNUMBER($E17),H17+14,"") | J17: =IF(NOT(ISNUMBER($E17)),"",IF($E17>=F17,"Done",F17-TODAY())) | K17: =IF(NOT(ISNUMBER($E17)),"",IF($E17>=G17,"Done",G17-TODAY())) | L17: =IF(NOT(ISNUMBER($E17)),"",IF($E17>=H17,"Done",H17-TODAY())) | M17: =IF(NOT(ISNUMBER($E17)),"",IF($E17>=I17,"Done",I17-TODAY()))
A18: Anicut Capital | B18: =IFERROR(IF(COUNTIF('Company list 1'!$A$7:$A$1048576,A18)+COUNTIF('Company list 2'!$A$7:$A$1048576,A18)+COUNTIF('Company list 3'!$A$7:$A$1048576, A18)=1, "Yes", "Error"),"Error") -> Yes | D18: =_xlfn.LET(_xlpm.L,IFERROR(_xlfn.XLOOKUP(A18,#REF!,#REF!),_xlfn.XLOOKUP(A18,'Company list 1'!A:A,'Company list 1'!C:C,"")),IF(_xlpm.L=0,"",_xlpm.L)) -> Priya Mam reach out | E18: =_xlfn.LET(_xlpm.d,IFERROR(_xlfn.XLOOKUP(A18,#REF!,#REF!),_xlfn.XLOOKUP(A18,'Company list 1'!A:A,'Company list 1'!D:D,"")),IF(_xlpm.d=0,"",_xlpm.d)) -> Priya Mam reach out | F18: =IF(ISNUMBER($E18),D18+14,"") | G18: =IF(ISNUMBER($E18),F18+14,"") | H18: =IF(ISNUMBER($E18),G18+14,"") | I18: =IF(ISNUMBER($E18),H18+14,"") | J18: =IF(NOT(ISNUMBER($E18)),"",IF($E18>=F18,"Done",F18-TODAY())) | K18: =IF(NOT(ISNUMBER($E18)),"",IF($E18>=G18,"Done",G18-TODAY())) | L18: =IF(NOT(ISNUMBER($E18)),"",IF($E18>=H18,"Done",H18-TODAY())) | M18: =IF(NOT(ISNUMBER($E18)),"",IF($E18>=I18,"Done",I18-TODAY()))
... A76: Al Dahra | B76: =IFERROR(IF(COUNTIF('Company list 1'!$A$7:$A$1048576,A76)+COUNTIF('Company list 2'!$A$7:$A$1048576,A76)+COUNTIF('Company list 3'!$A$7:$A$1048576, A76)=1, "Yes", "Error"),"Error") -> Yes | D76: =_xlfn.LET(_xlpm.L,IFERROR(_xlfn.XLOOKUP(A76,#REF!,#REF!),_xlfn.XLOOKUP(A76,'Company list 1'!A:A,'Company list 1'!C:C,"")),IF(_xlpm.L=0,"",_xlpm.L)) -> 46174 | E76: =_xlfn.LET(_xlpm.d,IFERROR(_xlfn.XLOOKUP(A76,#REF!,#REF!),_xlfn.XLOOKUP(A76,'Company list 1'!A:A,'Company list 1'!D:D,"")),IF(_xlpm.d=0,"",_xlpm.d)) -> Bounced | F76: =IF(ISNUMBER($E76),D76+14,"") | G76: =IF(ISNUMBER($E76),F76+14,"") | H76: =IF(ISNUMBER($E76),G76+14,"") | I76: =IF(ISNUMBER($E76),H76+14,"") | J76: =IF(NOT(ISNUMBER($E76)),"",IF($E76>=F76,"Done",F76-TODAY())) | K76: =IF(NOT(ISNUMBER($E76)),"",IF($E76>=G76,"Done",G76-TODAY())) | L76: =IF(NOT(ISNUMBER($E76)),"",IF($E76>=H76,"Done",H76-TODAY())) | M76: =IF(NOT(ISNUMBER($E76)),"",IF($E76>=I76,"Done",I76-TODAY()))
