Workbook

Sheet Master sheets and emailers >>>
B3: Ongoing | C3: Got response | D3: Bounced | E3: Total | F3: Response rate
A4: PE | B4: =COUNT('PE names final'!$D:$D) -> 47 | C4: =COUNTIF('PE names final'!$D:$D,"Got response") -> 21 | D4: =COUNTIF('PE names final'!$D:$D,"Bounced") -> 2 | E4: =SUM(B4:D4) -> 70 | F4: =IFERROR(C4/E4,0) -> 0.3
A5: PE porfolio | B5: =COUNT('PE porfolio names final'!$D:$D) -> 32 | C5: =COUNTIF('PE porfolio names final'!$D:$D,"Got response") -> 15 | D5: =COUNTIF('PE porfolio names final'!$D:$D,"Bounced") -> 6 | E5: =SUM(B5:D5) -> 53 | F5: =IFERROR(C5/E5,0) -> 0.28301887
A6: Total | B6: =SUM(B4:B5) -> 79 | C6: =SUM(C4:C5) -> 36 | D6: =SUM(D4:D5) -> 8 | E6: =SUM(E4:E5) -> 123 | F6: =IFERROR(C6/E6,0) -> 0.29268293

Sheet PE names final
A1: PE porfotio buyers - 22by7
A2: =COUNTA(A6:A1048576) -> 70
A5: Company Name | B5: HQ | C5: Initial email | D5: Status | E5: Website link | F5: Contact Name 1 | G5: Designation 1 | H5: Email Id 1 | I5: Linkedin 1 | J5: Contact Name 2 | K5: Designation 2 | L5: Email Id 2 | M5: Linkedin 2 | N5: Bucket
A6: Trunorth | B6: India | C6: 46034 | D6: 46091 | E6: https://www.truenorth.co.in/ | F6: Mahinder Singh Juneja | G6: Partner | H6: maninder@truenorth.co.in | I6: https://www.linkedin.com/in/maninder-singh-juneja-35a01a13/ | J6: Khushal Singla | K6: Private Credit Investment Professional | L6: khushal@truenorth.co.in | M6: https://www.linkedin.com/in/khushal-singla-656017166/ | N6: Indian PEs with related porfolio companies
A7: MC Partners | B7: USA | C7: 46055 | D7: Got response | E7: https://www.mcpartners.com/ | F7: Ryan Carr | G7: Partner | H7: rcarr@mcpartners.com | I7: https://www.linkedin.com/in/ryan-carr-b6453736/ | N7: Foreign PEs with related pofolio companies having Indian offices
A8: Norwest | B8: USA | C8: 46051 | D8: 46107 | E8: https://www.norwest.com/ | F8: Jon Kossow | G8: Managing Partner | H8: jkossow@nvp.com | I8: https://www.linkedin.com/in/jon-kossow-42706b2/ | N8: Foreign PEs with related pofolio companies having Indian offices
A9: Intel Capital | B9: USA | C9: 46051 | D9: 46107 | E9: https://www.intelcapital.com/ | F9: Aravind Bharadwaj | G9: Investment Partner | H9: aravind.bharadwaj@intel.com | I9: https://www.linkedin.com/in/aravindbharadwaj/ | N9: Foreign PEs with related pofolio companies having Indian offices
A10: The Stephens Group | B10: USA | C10: 46043 | D10: 46099 | E10: https://www.stephensgroup.com/ | F10: Jack Nadal | G10: Managing Director | H10: jnadal@stephensgroup.com | I10: https://www.linkedin.com/in/jack-nadal-7157b8a/ | N10: Foreign PEs with related pofolio companies having Indian offices
A11: VSS Capital Partners | B11: USA | C11: 46062 | D11: 46120 | E11: https://www.vss.com/ | F11: Jeffrey Stevenson | G11: Managing Partner | H11: stevensonj@vss.com | I11: https://www.linkedin.com/in/jeffrey-stevenson-8914318/ | N11: Foreign PEs with related pofolio companies having Indian offices
A12: Abry Partners | B12: USA | C12: 46051 | D12: 46107 | E12: https://abry.com/ | F12: Vidur Khatri | G12: Principal | H12: vkhatri@abry.com | I12: https://www.linkedin.com/in/vidur-khatri-52aa0946/ | N12: Foreign PEs with related pofolio companies having Indian offices
A13: Lightview Partners | B13: USA | C13: 46062 | D13: 46120 | E13: https://www.lightviewcapital.com/ | F13: Conor Mullett | G13: Co-Founder/Managing Director | H13: cmullett@lightviewcapital.com | I13: https://www.linkedin.com/in/conor-mullett-7b640b/ | N13: Foreign PEs with related pofolio companies having Indian offices
A14: Recognize | B14: USA | C14: 46062 | D14: Bounced | E14: https://recognize.com/ | F14: Muthu Kumaran | G14: Head of India Operations/Operating Partner | H14: muthu@recognize.com | I14: https://www.linkedin.com/in/muthu-kumaran-a616a616/ | N14: Foreign PEs with related pofolio companies having Indian offices
A15: Advent | B15: USA | C15: 46035 | D15: 46091 | E15: https://www.adventinternational.com/ | F15: Mohammed Anjarwala | G15: Partner | H15: manjarwala@adventinternational.com | I15: https://www.linkedin.com/in/anjarwala/ | N15: Foreign PE with potfolio companies not having Indian offices
A16: Kedaara | B16: India | C16: 46034 | D16: Got response | E16: https://kedaara.com/ | F16: Manish Kejriwal | G16: Founder/Managing Partner | H16: manish.kejriwal@kedaara.com | I16: https://www.linkedin.com/in/manish-kejriwal-1a7336/ | J16: Priyansh Changoiwala | K16: Associate | L16: priyansh.changoiwala@kedaara.com | M16: https://www.linkedin.com/in/priyansh-changoiwala-685280177/ | N16: Indian PE with unrelated potfolio companies
A17: 8 Roads | B17: Bermuda | C17: 46055 | D17: 46111 | E17: https://eightroads.com/en/ | F17: Gordon Zhang | G17: Partner | H17: gordon.zhang@eightroads.com | I17: https://www.linkedin.com/in/gordon-zhang-9490b3273/ | N17: Foreign PE with potfolio companies not having Indian offices
A18: Convergent Finance | B18: India | C18: 46034 | D18: 46091 | E18: https://convergentfinance.com/ | F18: Harsha Raghavan | G18: Managing Partner | H18: harsha@convergentfinance.com | I18: https://www.linkedin.com/in/harsha-raghavan-1218a11b5/ | N18: Indian PEs with unrelated potfolio companies
A19: Premji Invest | B19: India | C19: 46034 | D19: 46091 | E19: https://in.premjiinvest.com/ | F19: Kaveesh Chawla | G19: Partner | H19: kaveesh.chawla@premjiinvest.com | I19: https://www.linkedin.com/in/kaveeshchawla/ | N19: Indian PEs with unrelated potfolio companies
A20: Samara Capital | B20: India | C20: 46034 | D20: Got response | E20: https://samaracapital.com/ | F20: Manish Mehta | G20: Managing Director | H20: manish@samaracapital.com | I20: https://www.linkedin.com/in/manish-mehta-0883873/ | N20: Indian PEs with unrelated potfolio companies
A21: Evergreen Services Group | B21: USA | C21: 45974 | D21: Got response | E21: https://www.evergreensg.com/ | F21: Ramsey Sahyoun | G21: Co-founder/M&A Partner | H21: rsahyoun@evergreensg.com | I21: https://www.linkedin.com/in/ramsey-sahyoun-67b32683/ | N21: Foreign PE with potfolio companies not having Indian offices
A22: Creador | B22: Malysia | C22: 46055 | D22: 46111 | E22: https://creador.com/ | F22: Alberto Lazzari | G22: PE Professional | H22: a.lazzari@creador.com | I22: https://www.linkedin.com/in/alberto-lazzari-mba-217b944a/ | N22: Foreign PE with potfolio companies not having Indian offices
A23: Sunstone Partners | B23: USA | C23: 45974 | D23: Got response | E23: https://sunstonepartners.com/ | F23: Ankur Rathi | G23: Partner | H23: arathi@sunstonepartners.com | I23: https://www.linkedin.com/in/arathi2/ | N23: Foreign PE with potfolio companies not having Indian offices
A24: ChrysCapital | B24: Mauritius | C24: 46055 | D24: 46111 | E24: https://chryscapital.com/ | F24: Sanjiv Kaul | G24: Partner | H24: sanjiv@chryscapital.com | I24: https://www.linkedin.com/in/sanjiv-kaul-135b301a5/ | N24: Foreign PE with potfolio companies not having Indian offices
A25: Halyard Capital | B25: USA | C25: 46055 | D25: 46111 | E25: https://www.halyard.com/ | F25: Robert Nolan | G25: Managing Partner | H25: rnolan@halyard.com | I25: https://www.linkedin.com/in/robert-nolan10/ | N25: Foreign PE with potfolio companies not having Indian offices
A26: Navis Capital Partners | B26: Malaysia | C26: 46055 | D26: Got response | E26: https://www.naviscapital.com/ | F26: Gordon C. | G26: Operating Partner | H26: gchan@naviscapital.com | I26: https://www.linkedin.com/in/gordon-c-2118734/ | N26: Foreign PE with potfolio companies not having Indian offices
A27: Ascent Capital | B27: India | C27: 46034 | D27: 46091 | E27: https://ascentcapital.in/ | F27: Raja Kumar | G27: Founder/Managing Partner | H27: raja@ascentcapital.in | I27: https://www.linkedin.com/in/raja-kumar-455b7245/ | N27: Indian PEs with unrelated potfolio companies
A28: Gaja Capital | B28: India | C28: 46034 | D28: Got response | E28: https://gajacapital.com/ | F28: Sushane Chopra | G28: Partner | H28: sushane.chopra@gajacapital.com | I28: https://www.linkedin.com/in/sushane-chopra-b248334/ | N28: Indian PEs with unrelated potfolio companies
A29: Westbridge Capital | B29: India | C29: 46034 | D29: 46091 | E29: https://westbridgecap.com/ | F29: Sumir Chadha | G29: Co-founder/Managing Partner | H29: sumir.chadha@westbridgecap.com | I29: https://www.linkedin.com/in/sumir-chadha-bb8b563/ | N29: Indian PEs with unrelated potfolio companies
A30: Stakeboat Capital | B30: India | C30: 46034 | D30: Got response | E30: https://stakeboat.com/ | F30: Chandrasekar Kandasamy | G30: Managing Partner | H30: chandra@stakeboat.com | I30: https://www.linkedin.com/in/chandrasekar-kandasamy-4b8703/ | J30: Ram Pratheek Azendla | K30: Senior Associate | L30: pratheek@stakeboat.com | M30: https://www.linkedin.com/in/rampratheek/ | N30: Indian PEs with unrelated potfolio companies
A31: Prosperity7 Ventures | B31: Saudi Arabia | C31: 46055 | D31: 46111 | E31: https://www.prosperity7vc.com/ | F31: Abhishek Shukla | G31: Managing Director and Head of North America | H31: abhishek.shukla@p7vc.com | I31: https://www.linkedin.com/in/ashukla1/ | N31: Foreign PE with potfolio companies not having Indian offices
A32: Steadview Capital | B32: UK | C32: 46062 | D32: 46120 | E32: https://www.steadview.com/ | F32: Joy Bhakat | G32: Co-Founder/Head of Investments | H32: jbhakat@steadview.com | I32: https://www.linkedin.com/in/joy-bhakat-35895845/ | N32: Foreign PE with potfolio companies not having Indian offices
A33: Avataar Ventures | B33: India | C33: 46034 | D33: Got response | E33: https://www.avataar.vc/ | F33: Arjun Vikas | G33: Director | H33: arjun@avataar.vc | I33: https://www.linkedin.com/in/arjun-vikas-84118849/ | N33: Indian PEs with unrelated potfolio companies
A34: Affirma Capital | B34: Singapore | C34: 46062 | D34: Got response | E34: https://affirmacapital.com/ | F34: Ivo Philipps | G34: COO/Founding Partner | H34: ivo.philipps@affirmacapital.com | I34: https://www.linkedin.com/in/ivo-philipps-5a74244/ | N34: Foreign PE with potfolio companies having Indian offices
A35: Investcorp | B35: Bahrain | C35: 46034 | D35: 46091 | E35: https://www.investcorp.com/ | F35: Anshuman Goenka | G35: Partner | H35: agoenka@investcorp.com | I35: https://www.linkedin.com/in/anshuman-goenka-319435/ | N35: Indian PEs with unrelated potfolio companies
A36: BGF | B36: UK | C36: 46062 | D36: 46120 | E36: https://www.bgf.co.uk/ | F36: Pinesh Mehta | G36: Partner | H36: pinesh.mehta@bgf.co.uk | I36: https://www.linkedin.com/in/pinesh-mehta-29448a14/ | N36: Foreign PE with potfolio companies not having Indian offices
A37: Transom Capital | B37: USA | C37: 46035 | D37: 46091 | E37: https://transomcap.com/ | F37: Steve Kim | G37: Managing Director | H37: skim@transomcap.com | I37: https://www.linkedin.com/in/steve-kim-4194b29/ | N37: Foreign PE with potfolio companies not having Indian offices
A38: Runtide Capital | B38: USA | C38: 46035 | D38: Got response | E38: https://www.runtidecapital.com/ | F38: Robert Manning | G38: Managing Partner | H38: rmanning@runtidecapital.com | I38: https://www.linkedin.com/in/robert-manning-268203/ | N38: Foreign PE with potfolio companies not having Indian offices
A39: Great Hill Partners | B39: USA | C39: 46035 | D39: 46091 | E39: https://www.greathillpartners.com/ | F39: Atle Skalleberg | G39: Growth Partner | H39: askalleberg@greathillpartners.com | I39: https://www.linkedin.com/in/skalleberg/ | N39: Foreign PE with potfolio companies not having Indian offices
A40: Petros Partners | B40: USA | C40: 46035 | D40: 46091 | E40: https://www.petrospartners.com/ | F40: Mansoor Ghori | G40: Board Mamber/Co-Founder/Vice Chairman | H40: mansoor@petrospartners.com | I40: https://www.linkedin.com/in/mansoor-ghori-14474/ | N40: Foreign PE with potfolio companies not having Indian offices
A41: Arlington Capital Partners | B41: USA | C41: 46035 | D41: Got response | E41: https://arlingtoncap.com/ | F41: Ben Ramundo | G41: Managing Director | H41: bramundo@arlingtoncap.com | I41: https://www.linkedin.com/in/benjaminramundo89/ | N41: Foreign PE with potfolio companies not having Indian offices
A42: La Maison Partners | B42: France | C42: 46058 | D42: Got response | E42: https://www.lamaisonpartners.fr/en/ | F42: Long Zhou | G42: Investment Director | H42: l.zhou@lamaisonpartners.fr | I42: https://www.linkedin.com/in/long-zhou-44babb3b/ | N42: Foreign PE with potfolio companies not having Indian offices
A43: Insight Partners | B43: USA | C43: 46035 | D43: 46091 | E43: https://www.insightpartners.com/ | F43: Thilo Semmelbauer | G43: Managing Director | H43: tsemmelbauer@insightpartners.com | I43: https://www.linkedin.com/in/thilo/ | N43: Foreign PE with potfolio companies not having Indian offices
A44: Frontenac | B44: USA | C44: 46062 | D44: 46120 | E44: https://frontenac.com/ | F44: Walter Florence | G44: Managing Partner | H44: wflorence@frontenac.com | I44: https://www.linkedin.com/in/walterflorence/ | N44: Foreign PE with potfolio companies not having Indian offices
A45: PSP Partners | B45: USA | C45: 46062 | D45: 46120 | E45: https://www.psppartners.com/ | F45: Jon Skinner | G45: CEO | H45: jskinner@psppartners.com | I45: https://www.linkedin.com/in/jon-skinner-50a4422/ | N45: Foreign PE with potfolio companies not having Indian offices
A46: Newspring Holdings | B46: USA | C46: 46062 | D46: 46120 | E46: https://newspringcapital.com/ | F46: Greg Barger | G46: General Partner | H46: gbarger@newspringcapital.com | I46: https://www.linkedin.com/in/greg-barger-172b0617/ | N46: Foreign PE with potfolio companies not having Indian offices
A47: FFL Partners | B47: USA | C47: 46062 | D47: Got response | E47: https://fflpartners.com/ | F47: Chris Harris | G47: Managing Partner | H47: charris@fflpartners.com | I47: https://www.linkedin.com/in/chris-harris-1b730a6/ | N47: Foreign PE with potfolio companies not having Indian offices
A48: Agellus Capital | B48: USA | C48: 46062 | D48: Got response | E48: https://www.agellus.com/ | F48: Jeff Aiello | G48: Co-founder/Managing Partner | H48: jaiello@agellus.com | I48: https://www.linkedin.com/in/jeffaiello/ | N48: Foreign PE with potfolio companies not having Indian offices
A49: Virtuvian Partners | B49: UK | C49: 46062 | D49: 46120 | E49: https://www.vitruvianpartners.com/ | F49: Joe O'Mara | G49: Partner | H49: joe.omara@vitruvianpartners.com | I49: https://www.linkedin.com/in/joe-o-mara-7822073/ | N49: Foreign PE with potfolio companies not having Indian offices
A50: HIG Capital | B50: USA | C50: 46062 | D50: 46120 | E50: https://hig.com/ | F50: Micael Hagelin | G50: Managing Director | H50: mhagelin@higcapital.com | I50: https://www.linkedin.com/in/micael-hagelin-a9a85a/ | N50: Foreign PE with potfolio companies not having Indian offices
A51: Bregal Sagemount | B51: USA | C51: 46062 | D51: 46120 | E51: https://www.sagemount.com/ | F51: Michael Kosty | G51: Co-founder/Partner | H51: michael.kosty@sagemount.com | I51: https://www.linkedin.com/in/kostymichael/ | N51: Foreign PE with potfolio companies not having Indian offices
A52: Iverness Graham | B52: USA | C52: 46035 | D52: 46091 | E52: https://www.invernessgraham.com/ | F52: Steve Wood | G52: Founder | H52: swood@invernessgraham.com | I52: https://www.linkedin.com/in/steve-wood-33b1ab16/ | N52: Foreign PE with potfolio companies not having Indian offices
A53: Court Square | B53: USA | C53: 46035 | D53: Got response | E53: https://www.courtsquare.com/ | F53: Michael Delaney | G53: Managing Partner | H53: mdelaney@courtsquare.com | I53: https://www.linkedin.com/in/michael-delaney-9b185116/ | N53: Foreign PE with potfolio companies not having Indian offices
A54: Prospect Partners | B54: USA | C54: 46035 | D54: Got response | E54: https://prospect-partners.com/ | F54: Erik Maurer | G54: Partner | H54: emaurer@prospect-partners.com | I54: https://www.linkedin.com/in/erikmaurer/ | N54: Foreign PE with potfolio companies not having Indian offices
A55: L Squared Capital | B55: USA | C55: 46041 | D55: 46097 | E55: https://www.lsquaredcap.com/ | F55: Adam Kimura | G55: Managing Partner | H55: akimura@lsquaredcap.com | I55: https://www.linkedin.com/in/adam-kimura-28319011/ | N55: Foreign PE with potfolio companies not having Indian offices
A56: Perpetual Capital Partners | B56: USA | C56: 46062 | D56: 46120 | E56: https://perpetualcapitalpartners.com/ | F56: N/A | G56: N/A | H56: info@perpetualcap.com | I56: N/A | N56: Foreign PE with potfolio companies not having Indian offices
A57: Prarie Capital | B57: USA | C57: 46041 | D57: 46097 | E57: https://www.prairie-capital.com/ | F57: C. Bryan Daniels | G57: Founding Partner | H57: bdaniels@prairie-capital.com | I57: https://www.linkedin.com/in/c-bryan-daniels-841245127/ | N57: Foreign PE with potfolio companies not having Indian offices
A58: Oval Partners | B58: USA | C58: 46041 | D58: Got response | E58: https://www.ovalpartners.com/ | F58: John Knoll | G58: Co-Founder | H58: john@ovalpartners.com | I58: https://www.linkedin.com/in/john-knoll-18b0ba1/ | N58: Foreign PE with potfolio companies not having Indian offices
A59: Atlantic Street Capital | B59: USA | C59: 46041 | D59: 46097 | E59: https://www.atlanticstreetcapital.com/ | F59: Peter Huang | G59: Vice President | H59: phuang@atlanticstreetcapital.com | I59: https://www.linkedin.com/in/peter-david-huang/ | N59: Foreign PE with potfolio companies not having Indian offices
A60: Seaport Capital | B60: USA | C60: 46041 | D60: 46097 | E60: https://www.seaportcapital.com/ | F60: Jim Collis | G60: Partner | H60: jim@seaportcapital.com | I60: https://www.linkedin.com/in/jim-collis/ | N60: Foreign PE with potfolio companies not having Indian offices
A61: Northwest Equity Partners | B61: USA | C61: 46062 | D61: Bounced | E61: https://nep.com/ | F61: Tony Armand | G61: Partner | H61: tarmand@nep.com | I61: https://www.linkedin.com/in/tony-armand-989b9b12/ | N61: Foreign PE with potfolio companies not having Indian offices
A62: Trinity Hunt Partners | B62: USA | C62: 46041 | D62: 46097 | E62: https://www.trinityhunt.com/ | F62: Blake Apel | G62: Managing Partner | H62: bapel@trinityhunt.com | I62: https://www.linkedin.com/in/blake-apel-01855232/ | N62: Foreign PE with potfolio companies not having Indian offices
A63: SNH Capital Partners | B63: USA | C63: 46041 | D63: 46097 | E63: https://www.snhcapitalpartners.com/ | F63: Reddy Karri | G63: Sr. Operating Partner | H63: rkarri@snhcap.com | I63: https://www.linkedin.com/in/reddykarri/ | N63: Foreign PE with potfolio companies not having Indian offices
A64: HCAP Partners | B64: USA | C64: 46041 | D64: 46097 | E64: https://www.hcap.com/ | F64: Frank Mora | G64: Partner | H64: frank@hcap.com | I64: https://www.linkedin.com/in/frank-mora-53115bb/ | N64: Foreign PE with potfolio companies not having Indian offices
A65: Pfingsten Partners | B65: USA | C65: 46041 | D65: 46097 | E65: https://pfingsten.com/ | F65: John Underwood | G65: Senior Managing Director | H65: junderwood@pfingsten.com | I65: https://www.linkedin.com/in/john-underwood-32196054/ | N65: Foreign PE with potfolio companies not having Indian offices
A66: Stonecourt Capital | B66: USA | C66: 46041 | D66: 46097 | E66: https://www.stonecourtlp.com/ | F66: Harry Gillespie | G66: Vice President | H66: gillespie@stonecourtlp.com | I66: https://www.linkedin.com/in/harry-gillespie-b92220aa/ | N66: Foreign PE with potfolio companies not having Indian offices
A67: Fulcrum IT Partners | B67: Canada | C67: 46041 | D67: 46097 | E67: https://www.fulcrumitp.com/ | F67: Kyle Lazinger | G67: President | H67: kyle.lanzinger@fulcrumitp.com | I67: https://www.linkedin.com/in/harry-gillespie-b92220aa/ | N67: Foreign PE with potfolio companies not having Indian offices
A68: JM Financial | B68: India | C68: 46041 | D68: Got response | E68: https://www.jmfl.com/ | F68: Vinit Rai | G68: Managing Director | H68: vinit.rai@jmfl.com | I68: https://www.linkedin.com/in/raivinit/ | N68: Indian PEs with unrelated potfolio companies
A69: TA Associates | B69: USA | C69: 46058 | D69: 46114 | E69: https://www.ta.com/ | F69: Aditya Sharma | G69: Managing Director | H69: asharma@ta.com | I69: https://www.linkedin.com/in/aditya-sharma-ba8ab321/ | N69: Foreign PE with potfolio companies having Indian offices
A70: Bay Capital | B70: India | C70: 46062 | D70: 46120 | E70: https://bay-cap.com/ | F70: Siddharth Mehta | G70: Managing Director | H70: sid@bay-cap.com | I70: https://www.linkedin.com/in/siddharth-mehta-baycap/ | N70: Indian PEs with unrelated potfolio companies
A71: Barings Private Equity Partners India | B71: India | C71: 46064 | D71: 46120 | E71: https://www.bpepindia.com/ | F71: Varun Batra | G71: Partner | H71: varun.batra@bpepindia.com | I71: https://www.linkedin.com/in/varun-batra-2b699833/ | N71: Indian PEs with related porfolio companies
A72: Gulf Capital | B72: Abu Dhabi | C72: 46065 | D72: 46121 | E72: https://www.gulfcapital.com/ | F72: Mohammad Madani | G72: Managing Director | H72: mmadani@gulfcapital.com | I72: https://www.linkedin.com/in/mohammad-madani-2a47bb9/ | N72: Foreign PE with potfolio companies not having Indian offices
A73: Partners Group | B73: Switzerland | C73: 46065 | D73: Got response | E73: https://www.partnersgroup.com/en | F73: Vageesh Gupta | G73: Managing Director | H73: vageesh.gupta@partnersgroup.com | I73: https://www.linkedin.com/in/vageesh-gupta-a63909a/ | N73: Foreign PE with potfolio companies having Indian offices
A74: Multiples Private Equity | B74: India | C74: 46079 | D74: 46149 | E74: https://www.multiplesequity.com/ | F74: Mehul Agarwal | G74: Associate VP | H74: mehul.agarwal@multiplesequity.com | I74: https://www.linkedin.com/in/mehul-agarwal-8a231391/ | N74: Indian PEs with unrelated potfolio companies
A75: Apax | B75: UK | C75: 46106 | D75: Got response | E75: https://www.apax.com/ | F75: Harjot Dhaliwal | G75: Partner - India Head | H75: harjot.dhaliwal@apax.com | I75: https://www.linkedin.com/in/harjot-dhaliwal-691a6517/ | N75: Foreign PE with potfolio companies having Indian offices

Sheet PE porfolio names final
A1: PE porfotio buyers - 22by7
A2: Exchange rate as on date | B2: 90.26
A3: Revenue and headcount data taken from Inven unless specified
A4: =COUNTA(A8:A1048576) -> 60
A7: Company Name | B7: HQ | C7: Initial email | D7: Status | E7: Rationale | F7: Revenue from source | G7: Rev (INR Cr) | H7: Headcount | I7: Website link | J7: Contact Name 1 | K7: Designation 1 | L7: Email Id 1 | M7: Linkedin 1 | N7: Contact Name 2 | O7: Designation 2 | P7: Email Id 2 | Q7: Linkedin 2 | R7: Holding company | S7: Holding company website link | T7: Bucket
A8: Celebal Technologies | B8: India | C8: 46056 | D8: 46112 | E8: Similar services; Indian locations | F8: 2811 | G8: =F8/10 -> 281.1 | H8: 2893 | I8: https://celebaltech.com/ | J8: Anirudh Kala | K8: CEO | L8: anirudh@celebaltech.com | M8: https://www.linkedin.com/in/anirudhkala/ | R8: Norwest | S8: https://www.norwest.com/ | T8: Expand Indian presence
A9: NxtGen | B9: India | C9: 46062 | D9: Got response | E9: Similar services; Indian locations | F9: 2349 | G9: =F9/10 -> 234.9 | H9: 492 | I9: https://nxtgen.com/ | J9: Rajgopal A S | K9: CEO/Managing Director | L9: raj@nxtgen.com | M9: https://www.linkedin.com/in/rajgopal-as/ | R9: Intel Capital | S9: https://www.intelcapital.com/ | T9: Expand Indian presence
A10: Accion Labs | B10: USA | C10: 46062 | D10: Vishnu got response | E10: Similar services; Indian locations | F10: 273 | G10: =(F10*1000000*$B$2)/10000000 -> 2464.098 | H10: 2381 | I10: https://www.accionlabs.com/ | J10: Kinesh Doshi | K10: CEO/Co-Founder | L10: kinesh.doshi@accionlabs.com | M10: https://www.linkedin.com/in/kinesh-doshi/ | R10: Trunorth | S10: https://www.truenorth.co.in/ | T10: Expand Indian presence
A11: MorganFranklin Cyber | B11: USA | C11: 46062 | D11: 46120 | E11: Similar services; Indian locations | F11: 200 | G11: =(F11*1000000*$B$2)/10000000 -> 1805.2 | H11: 137 | I11: https://mfcyber.com/ | J11: Peter Schile | K11: Co-Founder/President | L11: pete.schile@morganfranklin.com | M11: https://www.linkedin.com/in/peterschile/ | R11: MC Partners | S11: https://www.mcpartners.com/ | T11: Expand Indian presence
A12: Armor Defense | B12: USA | C12: 46062 | D12: 46120 | E12: Similar services; Indian locations | F12: 21 | G12: =(F12*1000000*$B$2)/10000000 -> 189.546 | H12: 28 | I12: https://www.armor.com/ | J12: Ananya Amin | K12: Managing Director | L12: ananya.amin@armor.com | M12: https://www.linkedin.com/in/ananyaamin/ | R12: The Stephens Group | S12: https://www.stephensgroup.com/ | T12: Expand Indian presence
A13: Centroid Systems | B13: USA | C13: 46062 | D13: 46120 | E13: Similar services; Indian locations | F13: 57 | G13: =(F13*1000000*$B$2)/10000000 -> 514.482 | H13: 253 | I13: https://www.centroid.com/ | J13: Ken Bowles | K13: CFO | L13: ken.bowles@centroid.com | M13: https://www.linkedin.com/in/kenbowles/ | R13: VSS Capital Partners | S13: https://www.vss.com/ | T13: Expand Indian presence
A14: Blue Mantis | B14: USA | C14: 46062 | D14: 46120 | E14: Similar services; Indian locations | F14: 37 | G14: =(F14*1000000*$B$2)/10000000 -> 333.962 | H14: 514 | I14: https://www.bluemantis.com/ | J14: Jason Bernstein | K14: CFO | L14: jason.bernstein@bluemantis.com | M14: https://www.linkedin.com/in/jason-bernstein-71b8136/ | R14: Abry Partners | S14: https://abry.com/ | T14: Expand Indian presence
A15: Buchanan Technologies | B15: USA | C15: 46062 | D15: 46120 | E15: Similar services; Indian locations | F15: 75 | G15: =(F15*1000000*$B$2)/10000000 -> 676.95 | H15: 786 | I15: https://www.buchanan.com/ | J15: Manish Yadav | K15: Senior Vice President | L15: myadav@buchanan.com | M15: https://www.linkedin.com/in/manish-yadav-736580143/ | R15: Lightview Partners | S15: https://www.lightviewcapital.com/ | T15: Expand Indian presence
A16: SDG Corporation | B16: USA | C16: 46062 | D16: 46120 | E16: Similar services; Indian locations | F16: 56 | G16: =(F16*1000000*$B$2)/10000000 -> 505.456 | H16: 693 | I16: https://sdgc.com/ | J16: Ajay Gupta | K16: CEO | L16: ajay@sdgc.com | M16: https://www.linkedin.com/in/ajay-gupta-016846/ | R16: Recognize | S16: https://recognize.com/ | T16: Expand Indian presence
A17: Thrive | B17: USA | C17: 46062 | D17: Got response | E17: Similar services; APAC locations | F17: 400 | G17: =(F17*1000000*$B$2)/10000000 -> 3610.4 | H17: 1936 | I17: https://thrivenextgen.com/ | J17: Bill McLaughlin | K17: Board Member/CEO | L17: bmclaughlin@thrivenetworks.com | M17: https://www.linkedin.com/in/billmclaughlinmsp/ | R17: MC Partners | S17: https://www.mcpartners.com/ | T17: Expand Asian presence
A18: Nuspire | B18: USA | C18: 46064 | D18: 46120 | E18: Similar services | F18: 237 | G18: =(F18*1000000*$B$2)/10000000 -> 2139.162 | H18: 2429 | I18: https://security.pditechnologies.com/ | J18: Dan Hoban | K18: Executive Vice President | L18: dan.hoban@nuspire.com | M18: https://www.linkedin.com/in/danhoban/ | R18: Insight Partners | S18: https://www.insightpartners.com/ | T18: Offshore/onshore expansion
A19: Redhelm | B19: USA | C19: 46064 | D19: 46120 | E19: Similar services | F19: 250 | G19: =(F19*1000000*$B$2)/10000000 -> 2256.5 | H19: 344 | I19: https://redhelm.com/ | J19: James Wilson | K19: CEO | L19: jwilson@redhelm.com | M19: https://www.linkedin.com/in/james-arthur-wilson/ | R19: Frontenac | S19: https://frontenac.com/ | T19: Offshore/onshore expansion
A20: Integris | B20: USA | C20: 46064 | D20: Vishnu reached out | E20: Similar services | F20: 73 | G20: =(F20*1000000*$B$2)/10000000 -> 658.898 | H20: 1181 | I20: https://integrisit.com/ | J20: Glenn Mathis | K20: Board Member/CEO | L20: glenn.mathis@integrisit.com | M20: https://www.linkedin.com/in/glennmathis/ | R20: Frontenac | S20: https://frontenac.com/ | T20: Offshore/onshore expansion
A21: Ntiva | B21: USA | C21: 46064 | D21: Got response | E21: Similar services | F21: 58 | G21: =(F21*1000000*$B$2)/10000000 -> 523.508 | H21: 477 | I21: https://www.ntiva.com/ | J21: Kevin Cook | K21: CSO | L21: kevin.cook@ntiva.com | M21: https://www.linkedin.com/in/kevin-cook-ntiva/ | R21: PSP Partners | S21: https://www.psppartners.com/ | T21: Offshore/onshore expansion
A22: Magna5 | B22: USA | C22: 46064 | D22: Got response | E22: Similar services | F22: 31 | G22: =(F22*1000000*$B$2)/10000000 -> 279.806 | H22: 335 | I22: https://www.magna5.com/ | J22: Robert Farina | K22: CEO | L22: robert.farina@magna5.com | M22: https://www.linkedin.com/in/robert-farina-33065914/ | R22: Newspring Holdings | S22: https://newspringcapital.com/ | T22: Offshore/onshore expansion
A23: Abacus Group LLC | B23: USA | C23: 46064 | D23: Got response | E23: Similar services | F23: 66 | G23: =(F23*1000000*$B$2)/10000000 -> 595.716 | H23: 446 | I23: https://www.abacusgroupllc.com/ | J23: Anthony J. D'Ambrosia | K23: Board Member/CEO | L23: ajd@abacusgroupllc.com | M23: https://www.linkedin.com/in/anthonyjdambrosi/ | R23: FFL Group | S23: https://fflpartners.com/ | T23: Offshore/onshore expansion
A24: Compass MSP | B24: USA | C24: 46064 | D24: Got response from PE | E24: Similar services | F24: 28 | G24: =(F24*1000000*$B$2)/10000000 -> 252.728 | H24: 240 | I24: https://compassmsp.com/ | J24: Michael Rapp | K24: CEO | L24: mrapp@compassmsp.com | M24: https://www.linkedin.com/in/michaelrapp22/ | R24: Agellus Capital | S24: https://www.agellus.com/ | T24: Offshore/onshore expansion
A25: Meriplex | B25: USA | C25: 46064 | D25: 46120 | E25: Similar services | F25: 66 | G25: =(F25*1000000*$B$2)/10000000 -> 595.716 | H25: 578 | I25: https://meriplex.com/ | J25: Garrett Else | K25: CFO | L25: garrett.else@meriplex.com | M25: https://www.linkedin.com/in/garrettelse/ | R25: Virtuvian Partners | S25: https://www.vitruvianpartners.com/ | T25: Offshore/onshore expansion
A26: Ascend Technologies | B26: USA | C26: 46064 | D26: 46120 | E26: Similar services | F26: 35 | G26: =(F26*1000000*$B$2)/10000000 -> 315.91 | H26: 303 | I26: https://teamascend.com/ | J26: Amar K. Patel | K26: CEO | L26: apatel@teamascend.com | M26: https://www.linkedin.com/in/amar311/ | R26: MC Partners | S26: https://www.mcpartners.com/ | T26: Offshore/onshore expansion
A27: C3 Integrated Solutions | B27: USA | C27: 46064 | D27: 46120 | E27: Similar services | F27: 11 | G27: =(F27*1000000*$B$2)/10000000 -> 99.286 | H27: 123 | I27: https://c3isit.com/ | J27: Marc Pantoni | K27: CEO | L27: mpantoni@c3isit.com | M27: https://www.linkedin.com/in/marc-pantoni-99961363/ | R27: MC Partners | S27: https://www.mcpartners.com/ | T27: Offshore/onshore expansion
A28: Consortium | B28: USA | C28: 46064 | D28: 46120 | E28: Similar services | F28: 11 | G28: =(F28*1000000*$B$2)/10000000 -> 99.286 | H28: 78 | I28: https://consortium.net/ | J28: Nate Ungerott | K28: CEO | L28: nate.ungerott@consortium.net | M28: https://www.linkedin.com/in/nateungerott/ | R28: MC Partners | S28: https://www.mcpartners.com/ | T28: Offshore/onshore expansion
A29: Iron Bow Technologies | B29: USA | C29: 46064 | D29: 46120 | E29: Similar services | F29: 51 | G29: =(F29*1000000*$B$2)/10000000 -> 460.326 | H29: 922 | I29: https://ironbow.com/ | J29: Rene LaVigne | K29: CEO/President | L29: rene.lavigne@ironbow.com | M29: https://www.linkedin.com/in/rene-lavigne/ | R29: HIG Capital | S29: https://hig.com/ | T29: Offshore/onshore expansion
A30: Trace3 | B30: USA | C30: 46064 | D30: 46120 | E30: Similar services | F30: 226 | G30: =(F30*1000000*$B$2)/10000000 -> 2039.876 | H30: 1416 | I30: https://www.trace3.com/ | J30: Joe Quaglia | K30: CEO | L30: joe.quaglia@trace3.com | M30: https://www.linkedin.com/in/joequaglia/ | R30: HIG Capital | S30: https://hig.com/ | T30: Offshore/onshore expansion
A31: 360 Advanced | B31: USA | C31: 46064 | D31: Got response | E31: Similar services | F31: 11 | G31: =(F31*1000000*$B$2)/10000000 -> 99.286 | H31: 131 | I31: https://360advanced.com/ | J31: Gregory Bosl | K31: CFO | L31: gbosl@360advanced.com | M31: https://www.linkedin.com/in/gregorybosl/ | R31: Bregal Sagemount | S31: https://www.sagemount.com/ | T31: Offshore/onshore expansion
A32: CyberOne Security | B32: USA | C32: 46064 | D32: Got response | E32: Similar services | F32: 10 | G32: =(F32*1000000*$B$2)/10000000 -> 90.26 | H32: 77 | I32: https://cyberonesecurity.com/ | J32: Tera Davis | K32: CEO | L32: tera@cyberonesecurity.com | M32: https://www.linkedin.com/in/tera-davis-42aa0a1/ | R32: Bregal Sagemount | S32: https://www.sagemount.com/ | T32: Offshore/onshore expansion
A33: Corsica Technologies | B33: USA | C33: 46064 | D33: Bounced | E33: Similar services | F33: 9 | G33: =(F33*1000000*$B$2)/10000000 -> 81.234 | H33: 120 | I33: https://corsicatech.com/ | J33: Jennifer Lynn Parmenter | K33: CEO | L33: jparmenter@corsicatech.com | M33: https://www.linkedin.com/in/jennifer-lynn-parmenter-cma-52a75b13/ | R33: Iverness Graham | S33: https://www.invernessgraham.com/ | T33: Offshore/onshore expansion
A34: Entech | B34: USA | C34: 46064 | D34: 46120 | E34: Similar services | F34: 11 | G34: =(F34*1000000*$B$2)/10000000 -> 99.286 | H34: 72 | I34: https://www.entechus.com/ | J34: Buddy Martin | K34: CEO | L34: buddy@entechus.com | M34: https://www.linkedin.com/in/buddymartin/ | R34: Prospect Partners | S34: https://prospect-partners.com/ | T34: Offshore/onshore expansion
A35: Netrio | B35: USA | C35: 46064 | D35: Got response | E35: Similar services | F35: 100 | G35: =(F35*1000000*$B$2)/10000000 -> 902.6 | H35: 264 | I35: https://www.netrio.com/ | J35: Mark Clayman | K35: CEO | L35: mark.clayman@netrio.com | M35: https://www.linkedin.com/in/mark-clayman-70b55/ | R35: L Squared Capital | S35: https://www.lsquaredcap.com/ | T35: Offshore/onshore expansion
A36: Novatech | B36: USA | C36: 46064 | D36: Vishnu reached out | E36: Similar services | F36: 72 | G36: =(F36*1000000*$B$2)/10000000 -> 649.872 | H36: 721 | I36: https://novatech.net/ | J36: Jeff Hoctor | K36: CFO | L36: jhoctor@novatech.net | M36: https://www.linkedin.com/in/jeff-hoctor-cpa-b8b17a3/ | R36: Perpetual Capital Partners | S36: https://perpetualcapitalpartners.com/ | T36: Offshore/onshore expansion
A37: New Charter Technolgies | B37: USA | C37: 46064 | D37: 46120 | E37: Similar services | F37: 46 | G37: =(F37*1000000*$B$2)/10000000 -> 415.196 | H37: 75 | I37: https://www.newchartertech.com/ | J37: Peter Melby | K37: CEO | L37: peter@newchartertech.com | M37: https://www.linkedin.com/in/petermelby/ | R37: Oval Partners | S37: https://www.ovalpartners.com/ | T37: Offshore/onshore expansion
A38: CyberGuard Advantage | B38: USA | C38: 46064 | D38: Got response | E38: Similar services | F38: 9.2 | G38: =(F38*1000000*$B$2)/10000000 -> 83.0392 | H38: 52 | I38: https://www.cgcompliance.com/ | J38: Jim Jimenez | K38: Managing Partner | L38: jim.jimenez@cgcompliance.com | M38: https://www.linkedin.com/in/jim-jimenez-cpa-4b7a1ab/ | R38: Atlantic Street Capital | S38: https://www.atlanticstreetcapital.com/ | T38: Offshore/onshore expansion
A39: CyberlinkASP | B39: USA | C39: 46064 | D39: 46120 | E39: Similar services | F39: 11 | G39: =(F39*1000000*$B$2)/10000000 -> 99.286 | H39: 58 | I39: https://cyberlinkasp.com/ | J39: Kevin McGahey | K39: CFO | L39: kevin.mcgahey@cybasp.com | M39: https://www.linkedin.com/in/kevinmcgahey/ | R39: Seaport Capital | S39: https://www.seaportcapital.com/ | T39: Offshore/onshore expansion
A40: Coretelligent | B40: USA | C40: 46064 | D40: 46120 | E40: Similar services | F40: 29 | G40: =(F40*1000000*$B$2)/10000000 -> 261.754 | H40: 241 | I40: https://www.coretelligent.com/ | J40: Vijay Iyer | K40: CEO | L40: viyer@core.tech | M40: https://www.linkedin.com/in/vijay1balasubramanian/ | R40: Northwest Equity Partners | S40: https://nep.com/ | T40: Offshore/onshore expansion
A41: Dataprise | B41: USA | C41: 46064 | D41: 46120 | E41: Similar services | F41: N/A | G41: N/A | H41: 572 | I41: https://www.dataprise.com/ | J41: Siobhan de Leeuw | K41: CFO | L41: siobhan.deleeuw@dataprise.com | M41: https://www.linkedin.com/in/siobhan-de-leeuw-97234a4/ | R41: Trinity Hunt Partners | S41: https://www.trinityhunt.com/ | T41: Offshore/onshore expansion
A42: Five Nines | B42: USA | C42: 46064 | D42: 46120 | E42: Similar services | F42: 14 | G42: =(F42*1000000*$B$2)/10000000 -> 126.364 | H42: 158 | I42: https://fivenines.com/ | J42: Joel Friesen | K42: CEO | L42: joel@gonines.com | M42: https://www.linkedin.com/in/joel-friesen-9199a7a/ | R42: SNH Capital Partners | S42: https://www.snhcapitalpartners.com/ | T42: Offshore/onshore expansion
A43: Lumify | B43: USA | C43: 46064 | D43: 46120 | E43: Similar services | F43: 23 | G43: =(F43*1000000*$B$2)/10000000 -> 207.598 | H43: 236 | I43: https://www.lumificyber.com/ | J43: Michael Blain | K43: CFO | L43: michael@lumificyber.com | M43: https://www.linkedin.com/in/michael-blain-mba/ | R43: HCAP Partners | S43: https://www.hcap.com/ | T43: Offshore/onshore expansion
A44: NexusTek | B44: USA | C44: 46064 | D44: Bounced | E44: Similar services | F44: 34 | G44: =(F44*1000000*$B$2)/10000000 -> 306.884 | H44: 356 | I44: https://www.nexustek.com/ | J44: Hamilton Yu | K44: CEO | L44: hamilton.yu@nexustek.com | M44: https://www.linkedin.com/in/hamiltonyu/ | R44: Abry Partners | S44: https://abry.com/ | T44: Offshore/onshore expansion
A45: Omega Systems | B45: USA | C45: 46064 | D45: Bounced | E45: Similar services | F45: 18 | G45: =(F45*1000000*$B$2)/10000000 -> 162.468 | H45: 228 | I45: https://omegasystemscorp.com/ | J45: Mike Fuhrman | K45: CEO | L45: mfuhrman@omegasystemscorp.com | M45: https://www.linkedin.com/in/mfuhrman/ | R45: Pfingsten Partners | S45: https://pfingsten.com/ | T45: Offshore/onshore expansion
A46: Security Risk Advisors | B46: USA | C46: 46064 | D46: 46120 | E46: Similar services | F46: 30 | G46: =(F46*1000000*$B$2)/10000000 -> 270.78 | H46: 315 | I46: https://sra.io/ | J46: Tim Wainwright | K46: CEO | L46: tim.wainwright@sra.io | M46: https://www.linkedin.com/in/tim-wainwright-87a4a51/ | R46: Recognize | S46: https://recognize.com/ | T46: Offshore/onshore expansion
A47: 365 Data Centres | B47: USA | C47: 46064 | D47: 46120 | E47: Similar services | F47: 32 | G47: =(F47*1000000*$B$2)/10000000 -> 288.832 | H47: 181 | I47: https://365datacenters.com/ | J47: Steven Amelio | K47: CFO | L47: samelio@365datacenters.com | M47: https://www.linkedin.com/in/steven-amelio-70788b6/ | R47: Stonecourt Capital | S47: https://www.stonecourtlp.com/ | T47: Offshore/onshore expansion
A48: Advizex | B48: USA | C48: 46064 | D48: Bounced | E48: Similar services | F48: 36 | G48: =(F48*1000000*$B$2)/10000000 -> 324.936 | H48: 319 | I48: https://www.advizex.com/ | J48: C.R. Howdyshell | K48: CEO | L48: chowdyshell@advizex.com | M48: https://www.linkedin.com/in/c-r-howdyshell-2966ba1/ | R48: Fulcrum IT partners | S48: https://www.fulcrumitp.com/ | T48: Offshore/onshore expansion
A49: Fortress Security Risk Management | B49: USA | C49: 46064 | D49: 46120 | E49: Similar services | F49: 9 | G49: =(F49*1000000*$B$2)/10000000 -> 81.234 | H49: 47 | I49: https://fortresssrm.com/ | J49: Jess Walpole | K49: President | L49: jwalpole@fortresssrm.com | M49: https://www.linkedin.com/in/jesswalpole/ | R49: Fulcrum IT partners | S49: https://www.fulcrumitp.com/ | T49: Offshore/onshore expansion
A50: Blue Alliance | B50: USA | C50: 46064 | D50: Got response | E50: MSP holding company | F50: 25 | G50: =(F50*1000000*$B$2)/10000000 -> 225.65 | H50: 33 | I50: https://www.bluealliance.com/ | J50: Nick Recker | K50: CEO/Founder | L50: nick.recker@bluealliance.com | M50: https://www.linkedin.com/in/nickrecker/ | R50: Prarie Capital | S50: https://www.prairie-capital.com/ | T50: Offshore/onshore expansion
A51: Velosio | B51: USA | C51: 46064 | D51: Got response | E51: Diversified but offers similar services | F51: 63 | G51: =(F51*1000000*$B$2)/10000000 -> 568.638 | H51: 425 | I51: https://www.velosio.com/ | J51: Robbie Morrison | K51: CEO | L51: rmorrison@velosio.com | M51: https://www.linkedin.com/in/robbiemorrison/ | R51: Court Square | S51: https://www.courtsquare.com/ | T51: Offshore/onshore expansion
A52: I-Tracing | B52: France | C52: 46062 | D52: Got response | E52: Similar services; APAC locations | F52: 68 | G52: =(F52*1000000*$B$2)/10000000 -> 613.768 | H52: 506 | I52: https://i-tracing.com/ | J52: Benjamin Leclerc | K52: Group CFO | L52: bleclerc@i-tracing.com | M52: https://www.linkedin.com/in/benjamin-leclerc-07928b54/ | R52: La Maison Partners | S52: https://www.lamaisonpartners.fr/en/ | T52: Expand Asian presence
A53: Version 1 | B53: Ireland | C53: 46065 | D53: Vishnu got response | E53: Similar services; Indian locations | F53: 350 | G53: =(F53*1000000*$B$2)/10000000 -> 3159.1 | H53: 3635 | I53: https://www.version1.com/ | J53: Patrick Cooney | K53: Group CFO | L53: patrick.cooney@version1.com | M53: https://www.linkedin.com/in/cooneypatrick/ | R53: Partners Group | S53: https://www.partnersgroup.com/ | T53: Expand Indian presence
A54: Ensono | B54: USA | C54: 46069 | D54: 46125 | E54: Similar services; Indian locations | F54: 323 | G54: =(F54*1000000*$B$2)/10000000 -> 2915.398 | H54: 3437 | I54: https://www.ensono.com/ | J54: Veena Khandke | K54: India managing director/SVP | L54: veena.khandke@ensono.com | M54: https://www.linkedin.com/in/veenakhandke/ | R54: KKR | S54: https://www.kkr.com/ | T54: Expand Indian presence
A55: First Meridian | B55: India | C55: 46070 | D55: 46126 | E55: Staffing; Indian locations | F55: 44783 | G55: =F55/10 -> 4478.3 | H55: 483 | I55: https://firstmeridian.com/ | J55: Satish Srinivasan | K55: CFO | L55: satish.srinivasan@firstmeridian.com | M55: https://www.linkedin.com/in/satish-srinivasan-9792849b/ | R55: Samara Capital | S55: https://samaracapital.com/ | T55: Expand Indian presence
A56: Sutherland Global | B56: USA | C56: 46079 | E56: Similar services; Indian locations | F56: 4116 | G56: =F56/10 -> 411.6 | H56: 64161 | I56: https://www.sutherlandglobal.com/ | J56: Jim Lusk | K56: CFO/Executive VP | L56: jim.lusk@sutherlandglobal.com | M56: https://www.linkedin.com/in/jim-lusk/ | N56: Rajesh Mohan Chatterjee | O56: Head of Finance/VP | P56: rajesh.chatterjee@sutherlandglobal.com | Q56: https://www.linkedin.com/in/rajesh-mohan-chatterjee-5ba2bb5/ | R56: Affirma Capital | S56: https://affirmacapital.com/ | T56: Expand Indian presence
A57: RMSI | B57: India | C57: 46079 | D57: Bounced | E57: Similar services; Indian locations | F57: 6247 | G57: =F57/10 -> 624.7 | H57: 6325 | I57: https://www.rmsi.com/ | J57: Navneet Gupta | K57: CFO/VP | L57: navneet.gupta@rmsi.com | M57: https://www.linkedin.com/in/navneet-gupta-ca/ | R57: Affirma Capital | S57: https://affirmacapital.com/ | T57: Expand Indian presence
A58: Strateq Group Of Companies | B58: Malaysia | C58: 46079 | D58: 46149 | E58: Similar services | F58: 48 | G58: =(F58*1000000*$B$2)/10000000 -> 433.248 | H58: 416 | I58: https://strateqgroup.com/home/ | J58: Tan Soo Li | K58: Head of Finance | L58: tansooli@strateqgroup.com | M58: https://www.linkedin.com/in/tan-soo-li-19b736a/ | R58: Navis Capital Partners | S58: https://www.naviscapital.com/ | T58: Expand Asian presence
A59: Security HQ | B59: UK | C59: 46105 | D59: Vishnu got response | E59: Similar services; Indian locations | F59: N/A | G59: N/A | H59: 503 | I59: https://www.securityhq.com/ | J59: Sanket Khanolkar | K59: CPO/APAC SVP | L59: sanket@securityhq.com | M59: https://www.linkedin.com/in/sanket-khanolkar-0705b221/ | R59: Growth Capital Partners | S59: https://www.growthcapital.co.uk/ | T59: Expand Indian presence
A60: Straive | B60: Singapore | C60: 46105 | D60: Got response | E60: Similar services; Indian locations | F60: N/A | G60: N/A | H60: 13071 | I60: https://www.straive.com/ | J60: Kumar Subramaniam | K60: Chief Risk Officer | L60: kumar.subramaniam@straive.com | M60: https://www.linkedin.com/in/kumarsb/ | R60: EQT | S60: https://eqtgroup.com/eqt-private-capital-asia | T60: Expand Indian presence
A61: Thoughtworks | B61: USA | C61: 46106 | D61: 46163 | E61: Similar services; Indian locations | F61: N/A | G61: N/A | H61: 12368 | I61: https://www.thoughtworks.com/ | J61: Erin Cummins | K61: CFO | L61: ecummins@thoughtworks.com | M61: https://www.linkedin.com/in/erin-cummins-77429547/ | R61: Apax | S61: https://www.apax.com/ | T61: Expand Indian presence
A62: Infogain | B62: USA | C62: 46106 | D62: 46163 | E62: Similar services; Indian locations | F62: N/A | G62: N/A | H62: 6001 | I62: https://www.infogain.com/ | J62: Kulesh Bansal | K62: CFO | L62: kulesh.bansal@infogain.com | M62: https://www.linkedin.com/in/kulesh-bansal-11158611/ | R62: Apax | S62: https://www.apax.com/ | T62: Expand Indian presence
A63: Cyderes | B63: USA | C63: 46106 | D63: 46163 | E63: Similar services; Indian locations | F63: N/A | G63: N/A | H63: 922 | I63: https://www.cyderes.com/ | J63: Nathan Brady | K63: CFO | L63: nate.brady@cyderes.com | M63: https://www.linkedin.com/in/brady-nate/ | R63: Apax | S63: https://www.apax.com/ | T63: Expand Indian presence
A64: Global Logic | B64: USA | C64: 46106 | D64: Bounced | E64: Similar services; Indian locations | F64: N/A | G64: N/A | H64: 34840 | I64: https://www.globallogic.com/ | J64: Vaibhav Sharma | K64: CFO | L64: vaibhav.sharma14@globallogic.com | M64: https://www.linkedin.com/in/linkvaibhavsharma/ | R64: Apax | S64: https://www.apax.com/ | T64: Expand Indian presence
A65: Park Place Technologies | B65: USA | C65: 46106 | D65: Got response | E65: Similar services; Indian locations | F65: N/A | G65: N/A | H65: 2375 | I65: https://www.parkplacetechnologies.com/ | J65: Kelly Greene | K65: VP Corporate Development | L65: kgreene@parkplacetech.com | M65: https://www.linkedin.com/in/kelisegreene/ | R65: Warburg Pincus | S65: https://warburgpincus.com/ | T65: Expand Indian presence
A66: Service express | B66: USA | C66: 46106 | D66: 46163 | E66: Similar services; Indian locations | F66: N/A | G66: N/A | H66: 1289 | I66: https://serviceexpress.com/ | J66: Julie Ausherman | K66: CFO | L66: jausherman@serviceexpress.com | M66: https://www.linkedin.com/in/julie-ausherman-4234772/ | R66: Warburg Pincus | S66: https://warburgpincus.com/ | T66: Expand Indian presence
A67: In2IT Technologies | B67: India | C67: 46163 | D67: Got response | E67: Similar services; Indian locations | F67: 69 | G67: =(F67*1000000*$B$2)/10000000 -> 622.794 | H67: 671 | I67: https://www.in2ittech.com/ | J67: Vishal Barapatre | K67: Group CTO | L67: vishal@in2ittech.com | M67: https://www.linkedin.com/in/vishal-barapatre/ | R67: NewGX Capital Group | S67: https://newgx.co.za/ | T67: Expand Indian presence

Sheet Emailing schedule
A1: Next set of emails due in (days) | C1: =MIN(J7:M1048576) -> 0 | D1: Count | E1: =SUBTOTAL(3,A7:A1048576) -> 130
D2: Check | E2: =E1-'PE names final'!A2-'PE porfolio names final'!A4 -> 0
B5: =IF(COUNTIF(B7:B1048576,"Error")>0,"Error", "Go") -> Go | C5: =IF(COUNTIF(C7:C1048576,"Error")>0,"Error", "Go") -> Go | E5: =IF(COUNTIF(E7:E1048576,"Error")>0,"Error", "Go") -> Go
A6: Company name | B6: Check to previous page | C6: Regarding | D6: Initial date | E6: Status | F6: Bi-weekly follow up | G6: Bi-weekly follow up | H6: Bi-weekly follow up | I6: Bi-weekly follow up | J6: Follow ups (in days)
A7: Trunorth | B7: =IF(COUNTIF('PE names final'!A:A, A7)+COUNTIF('PE porfolio names final'!A:A,A7)=1, "Yes", "Error") -> Yes | C7: {=_xlfn.IFS(AND(COUNTIF('PE names final'!A:A,A7)>0,COUNTIF('PE porfolio names final'!A:A,A7)>0),"Error",COUNTIF('PE names final'!A:A,A7)>0,"PE",COUNTIF('PE porfolio names final'!A:A,A7)>0,"Portfolio",TRUE,"")} -> PE | D7: =_xlfn.LET(_xlpm.L,IFERROR(_xlfn.XLOOKUP(A7,'PE names final'!A:A,'PE names final'!C:C),_xlfn.XLOOKUP(A7,'PE porfolio names final'!A:A,'PE porfolio names final'!C:C,"")),IF(_xlpm.L=0,"",_xlpm.L)) -> 46034 | E7: =_xlfn.LET(_xlpm.d,IFERROR(_xlfn.XLOOKUP(A7,'PE names final'!A:A,'PE names final'!D:D),_xlfn.XLOOKUP(A7,'PE porfolio names final'!A:A,'PE porfolio names final'!D:D,"")),IF(_xlpm.d=0,"",IF(_xlpm.d<D7,"Error",_xlpm.d))) -> 46091 | F7: =IF(ISNUMBER($E7),D7+14,"") -> 46048 | G7: =IF(ISNUMBER($E7),F7+14,"") -> 46062 | H7: =IF(ISNUMBER($E7),G7+14,"") -> 46076 | I7: =IF(ISNUMBER($E7),H7+14,"") -> 46090 | J7: =IF(NOT(ISNUMBER($E7)),"",IF($E7>=F7,"Done",F7-TODAY())) -> Done | K7: =IF(NOT(ISNUMBER($E7)),"",IF($E7>=G7,"Done",G7-TODAY())) -> Done | L7: =IF(NOT(ISNUMBER($E7)),"",IF($E7>=H7,"Done",H7-TODAY())) -> Done | M7: =IF(NOT(ISNUMBER($E7)),"",IF($E7>=I7,"Done",I7-TODAY())) -> Done
A8: MC Partners | B8: =IF(COUNTIF('PE names final'!A:A, A8)+COUNTIF('PE porfolio names final'!A:A,A8)=1, "Yes", "Error") -> Yes | C8: {=_xlfn.IFS(AND(COUNTIF('PE names final'!A:A,A8)>0,COUNTIF('PE porfolio names final'!A:A,A8)>0),"PE & Portfolio",COUNTIF('PE names final'!A:A,A8)>0,"PE",COUNTIF('PE porfolio names final'!A:A,A8)>0,"Portfolio",TRUE,"")} -> PE | D8: =_xlfn.LET(_xlpm.L,IFERROR(_xlfn.XLOOKUP(A8,'PE names final'!A:A,'PE names final'!C:C),_xlfn.XLOOKUP(A8,'PE porfolio names final'!A:A,'PE porfolio names final'!C:C,"")),IF(_xlpm.L=0,"",_xlpm.L)) -> 46055 | E8: =_xlfn.LET(_xlpm.d,IFERROR(_xlfn.XLOOKUP(A8,'PE names final'!A:A,'PE names final'!D:D),_xlfn.XLOOKUP(A8,'PE porfolio names final'!A:A,'PE porfolio names final'!D:D,"")),IF(_xlpm.d=0,"",IF(_xlpm.d<D8,"Error",_xlpm.d))) -> Got response | F8: =IF(ISNUMBER($E8),D8+14,"") | G8: =IF(ISNUMBER($E8),F8+14,"") | H8: =IF(ISNUMBER($E8),G8+14,"") | I8: =IF(ISNUMBER($E8),H8+14,"") | J8: =IF(NOT(ISNUMBER($E8)),"",IF($E8>=F8,"Done",F8-TODAY())) | K8: =IF(NOT(ISNUMBER($E8)),"",IF($E8>=G8,"Done",G8-TODAY())) | L8: =IF(NOT(ISNUMBER($E8)),"",IF($E8>=H8,"Done",H8-TODAY())) | M8: =IF(NOT(ISNUMBER($E8)),"",IF($E8>=I8,"Done",I8-TODAY()))
A9: Norwest | B9: =IF(COUNTIF('PE names final'!A:A, A9)+COUNTIF('PE porfolio names final'!A:A,A9)=1, "Yes", "Error") -> Yes | C9: {=_xlfn.IFS(AND(COUNTIF('PE names final'!A:A,A9)>0,COUNTIF('PE porfolio names final'!A:A,A9)>0),"PE & Portfolio",COUNTIF('PE names final'!A:A,A9)>0,"PE",COUNTIF('PE porfolio names final'!A:A,A9)>0,"Portfolio",TRUE,"")} -> PE | D9: =_xlfn.LET(_xlpm.L,IFERROR(_xlfn.XLOOKUP(A9,'PE names final'!A:A,'PE names final'!C:C),_xlfn.XLOOKUP(A9,'PE porfolio names final'!A:A,'PE porfolio names final'!C:C,"")),IF(_xlpm.L=0,"",_xlpm.L)) -> 46051 | E9: =_xlfn.LET(_xlpm.d,IFERROR(_xlfn.XLOOKUP(A9,'PE names final'!A:A,'PE names final'!D:D),_xlfn.XLOOKUP(A9,'PE porfolio names final'!A:A,'PE porfolio names final'!D:D,"")),IF(_xlpm.d=0,"",IF(_xlpm.d<D9,"Error",_xlpm.d))) -> 46107 | F9: =IF(ISNUMBER($E9),D9+14,"") -> 46065 | G9: =IF(ISNUMBER($E9),F9+14,"") -> 46079 | H9: =IF(ISNUMBER($E9),G9+14,"") -> 46093 | I9: =IF(ISNUMBER($E9),H9+14,"") -> 46107 | J9: =IF(NOT(ISNUMBER($E9)),"",IF($E9>=F9,"Done",F9-TODAY())) -> Done | K9: =IF(NOT(ISNUMBER($E9)),"",IF($E9>=G9,"Done",G9-TODAY())) -> Done | L9: =IF(NOT(ISNUMBER($E9)),"",IF($E9>=H9,"Done",H9-TODAY())) -> Done | M9: =IF(NOT(ISNUMBER($E9)),"",IF($E9>=I9,"Done",I9-TODAY())) -> Done
A10: Intel Capital | B10: =IF(COUNTIF('PE names final'!A:A, A10)+COUNTIF('PE porfolio names final'!A:A,A10)=1, "Yes", "Error") -> Yes | C10: {=_xlfn.IFS(AND(COUNTIF('PE names final'!A:A,A10)>0,COUNTIF('PE porfolio names final'!A:A,A10)>0),"PE & Portfolio",COUNTIF('PE names final'!A:A,A10)>0,"PE",COUNTIF('PE porfolio names final'!A:A,A10)>0,"Portfolio",TRUE,"")} -> PE | D10: =_xlfn.LET(_xlpm.L,IFERROR(_xlfn.XLOOKUP(A10,'PE names final'!A:A,'PE names final'!C:C),_xlfn.XLOOKUP(A10,'PE porfolio names final'!A:A,'PE porfolio names final'!C:C,"")),IF(_xlpm.L=0,"",_xlpm.L)) -> 46051 | E10: =_xlfn.LET(_xlpm.d,IFERROR(_xlfn.XLOOKUP(A10,'PE names final'!A:A,'PE names final'!D:D),_xlfn.XLOOKUP(A10,'PE porfolio names final'!A:A,'PE porfolio names final'!D:D,"")),IF(_xlpm.d=0,"",IF(_xlpm.d<D10,"Error",_xlpm.d))) -> 46107 | F10: =IF(ISNUMBER($E10),D10+14,"") -> 46065 | G10: =IF(ISNUMBER($E10),F10+14,"") -> 46079 | H10: =IF(ISNUMBER($E10),G10+14,"") -> 46093 | I10: =IF(ISNUMBER($E10),H10+14,"") -> 46107 | J10: =IF(NOT(ISNUMBER($E10)),"",IF($E10>=F10,"Done",F10-TODAY())) -> Done | K10: =IF(NOT(ISNUMBER($E10)),"",IF($E10>=G10,"Done",G10-TODAY())) -> Done | L10: =IF(NOT(ISNUMBER($E10)),"",IF($E10>=H10,"Done",H10-TODAY())) -> Done | M10: =IF(NOT(ISNUMBER($E10)),"",IF($E10>=I10,"Done",I10-TODAY())) -> Done
A11: The Stephens Group | B11: =IF(COUNTIF('PE names final'!A:A, A11)+COUNTIF('PE porfolio names final'!A:A,A11)=1, "Yes", "Error") -> Yes | C11: {=_xlfn.IFS(AND(COUNTIF('PE names final'!A:A,A11)>0,COUNTIF('PE porfolio names final'!A:A,A11)>0),"PE & Portfolio",COUNTIF('PE names final'!A:A,A11)>0,"PE",COUNTIF('PE porfolio names final'!A:A,A11)>0,"Portfolio",TRUE,"")} -> PE | D11: =_xlfn.LET(_xlpm.L,IFERROR(_xlfn.XLOOKUP(A11,'PE names final'!A:A,'PE names final'!C:C),_xlfn.XLOOKUP(A11,'PE porfolio names final'!A:A,'PE porfolio names final'!C:C,"")),IF(_xlpm.L=0,"",_xlpm.L)) -> 46043 | E11: =_xlfn.LET(_xlpm.d,IFERROR(_xlfn.XLOOKUP(A11,'PE names final'!A:A,'PE names final'!D:D),_xlfn.XLOOKUP(A11,'PE porfolio names final'!A:A,'PE porfolio names final'!D:D,"")),IF(_xlpm.d=0,"",IF(_xlpm.d<D11,"Error",_xlpm.d))) -> 46099 | F11: =IF(ISNUMBER($E11),D11+14,"") -> 46057 | G11: =IF(ISNUMBER($E11),F11+14,"") -> 46071 | H11: =IF(ISNUMBER($E11),G11+14,"") -> 46085 | I11: =IF(ISNUMBER($E11),H11+14,"") -> 46099 | J11: =IF(NOT(ISNUMBER($E11)),"",IF($E11>=F11,"Done",F11-TODAY())) -> Done | K11: =IF(NOT(ISNUMBER($E11)),"",IF($E11>=G11,"Done",G11-TODAY())) -> Done | L11: =IF(NOT(ISNUMBER($E11)),"",IF($E11>=H11,"Done",H11-TODAY())) -> Done | M11: =IF(NOT(ISNUMBER($E11)),"",IF($E11>=I11,"Done",I11-TODAY())) -> Done
A12: VSS Capital Partners | B12: =IF(COUNTIF('PE names final'!A:A, A12)+COUNTIF('PE porfolio names final'!A:A,A12)=1, "Yes", "Error") -> Yes | C12: {=_xlfn.IFS(AND(COUNTIF('PE names final'!A:A,A12)>0,COUNTIF('PE porfolio names final'!A:A,A12)>0),"PE & Portfolio",COUNTIF('PE names final'!A:A,A12)>0,"PE",COUNTIF('PE porfolio names final'!A:A,A12)>0,"Portfolio",TRUE,"")} -> PE | D12: =_xlfn.LET(_xlpm.L,IFERROR(_xlfn.XLOOKUP(A12,'PE names final'!A:A,'PE names final'!C:C),_xlfn.XLOOKUP(A12,'PE porfolio names final'!A:A,'PE porfolio names final'!C:C,"")),IF(_xlpm.L=0,"",_xlpm.L)) -> 46062 | E12: =_xlfn.LET(_xlpm.d,IFERROR(_xlfn.XLOOKUP(A12,'PE names final'!A:A,'PE names final'!D:D),_xlfn.XLOOKUP(A12,'PE porfolio names final'!A:A,'PE porfolio names final'!D:D,"")),IF(_xlpm.d=0,"",IF(_xlpm.d<D12,"Error",_xlpm.d))) -> 46120 | F12: =IF(ISNUMBER($E12),D12+14,"") -> 46076 | G12: =IF(ISNUMBER($E12),F12+14,"") -> 46090 | H12: =IF(ISNUMBER($E12),G12+14,"") -> 46104 | I12: =IF(ISNUMBER($E12),H12+14,"") -> 46118 | J12: =IF(NOT(ISNUMBER($E12)),"",IF($E12>=F12,"Done",F12-TODAY())) -> Done | K12: =IF(NOT(ISNUMBER($E12)),"",IF($E12>=G12,"Done",G12-TODAY())) -> Done | L12: =IF(NOT(ISNUMBER($E12)),"",IF($E12>=H12,"Done",H12-TODAY())) -> Done | M12: =IF(NOT(ISNUMBER($E12)),"",IF($E12>=I12,"Done",I12-TODAY())) -> Done
A13: Abry Partners | B13: =IF(COUNTIF('PE names final'!A:A, A13)+COUNTIF('PE porfolio names final'!A:A,A13)=1, "Yes", "Error") -> Yes | C13: {=_xlfn.IFS(AND(COUNTIF('PE names final'!A:A,A13)>0,COUNTIF('PE porfolio names final'!A:A,A13)>0),"PE & Portfolio",COUNTIF('PE names final'!A:A,A13)>0,"PE",COUNTIF('PE porfolio names final'!A:A,A13)>0,"Portfolio",TRUE,"")} -> PE | D13: =_xlfn.LET(_xlpm.L,IFERROR(_xlfn.XLOOKUP(A13,'PE names final'!A:A,'PE names final'!C:C),_xlfn.XLOOKUP(A13,'PE porfolio names final'!A:A,'PE porfolio names final'!C:C,"")),IF(_xlpm.L=0,"",_xlpm.L)) -> 46051 | E13: =_xlfn.LET(_xlpm.d,IFERROR(_xlfn.XLOOKUP(A13,'PE names final'!A:A,'PE names final'!D:D),_xlfn.XLOOKUP(A13,'PE porfolio names final'!A:A,'PE porfolio names final'!D:D,"")),IF(_xlpm.d=0,"",IF(_xlpm.d<D13,"Error",_xlpm.d))) -> 46107 | F13: =IF(ISNUMBER($E13),D13+14,"") -> 46065 | G13: =IF(ISNUMBER($E13),F13+14,"") -> 46079 | H13: =IF(ISNUMBER($E13),G13+14,"") -> 46093 | I13: =IF(ISNUMBER($E13),H13+14,"") -> 46107 | J13: =IF(NOT(ISNUMBER($E13)),"",IF($E13>=F13,"Done",F13-TODAY())) -> Done | K13: =IF(NOT(ISNUMBER($E13)),"",IF($E13>=G13,"Done",G13-TODAY())) -> Done | L13: =IF(NOT(ISNUMBER($E13)),"",IF($E13>=H13,"Done",H13-TODAY())) -> Done | M13: =IF(NOT(ISNUMBER($E13)),"",IF($E13>=I13,"Done",I13-TODAY())) -> Done
A14: Lightview Partners | B14: =IF(COUNTIF('PE names final'!A:A, A14)+COUNTIF('PE porfolio names final'!A:A,A14)=1, "Yes", "Error") -> Yes | C14: {=_xlfn.IFS(AND(COUNTIF('PE names final'!A:A,A14)>0,COUNTIF('PE porfolio names final'!A:A,A14)>0),"PE & Portfolio",COUNTIF('PE names final'!A:A,A14)>0,"PE",COUNTIF('PE porfolio names final'!A:A,A14)>0,"Portfolio",TRUE,"")} -> PE | D14: =_xlfn.LET(_xlpm.L,IFERROR(_xlfn.XLOOKUP(A14,'PE names final'!A:A,'PE names final'!C:C),_xlfn.XLOOKUP(A14,'PE porfolio names final'!A:A,'PE porfolio names final'!C:C,"")),IF(_xlpm.L=0,"",_xlpm.L)) -> 46062 | E14: =_xlfn.LET(_xlpm.d,IFERROR(_xlfn.XLOOKUP(A14,'PE names final'!A:A,'PE names final'!D:D),_xlfn.XLOOKUP(A14,'PE porfolio names final'!A:A,'PE porfolio names final'!D:D,"")),IF(_xlpm.d=0,"",IF(_xlpm.d<D14,"Error",_xlpm.d))) -> 46120 | F14: =IF(ISNUMBER($E14),D14+14,"") -> 46076 | G14: =IF(ISNUMBER($E14),F14+14,"") -> 46090 | H14: =IF(ISNUMBER($E14),G14+14,"") -> 46104 | I14: =IF(ISNUMBER($E14),H14+14,"") -> 46118 | J14: =IF(NOT(ISNUMBER($E14)),"",IF($E14>=F14,"Done",F14-TODAY())) -> Done | K14: =IF(NOT(ISNUMBER($E14)),"",IF($E14>=G14,"Done",G14-TODAY())) -> Done | L14: =IF(NOT(ISNUMBER($E14)),"",IF($E14>=H14,"Done",H14-TODAY())) -> Done | M14: =IF(NOT(ISNUMBER($E14)),"",IF($E14>=I14,"Done",I14-TODAY())) -> Done
A15: Recognize | B15: =IF(COUNTIF('PE names final'!A:A, A15)+COUNTIF('PE porfolio names final'!A:A,A15)=1, "Yes", "Error") -> Yes | C15: {=_xlfn.IFS(AND(COUNTIF('PE names final'!A:A,A15)>0,COUNTIF('PE porfolio names final'!A:A,A15)>0),"PE & Portfolio",COUNTIF('PE names final'!A:A,A15)>0,"PE",COUNTIF('PE porfolio names final'!A:A,A15)>0,"Portfolio",TRUE,"")} -> PE | D15: =_xlfn.LET(_xlpm.L,IFERROR(_xlfn.XLOOKUP(A15,'PE names final'!A:A,'PE names final'!C:C),_xlfn.XLOOKUP(A15,'PE porfolio names final'!A:A,'PE porfolio names final'!C:C,"")),IF(_xlpm.L=0,"",_xlpm.L)) -> 46062 | E15: =_xlfn.LET(_xlpm.d,IFERROR(_xlfn.XLOOKUP(A15,'PE names final'!A:A,'PE names final'!D:D),_xlfn.XLOOKUP(A15,'PE porfolio names final'!A:A,'PE porfolio names final'!D:D,"")),IF(_xlpm.d=0,"",IF(_xlpm.d<D15,"Error",_xlpm.d))) -> Bounced | F15: =IF(ISNUMBER($E15),D15+14,"") | G15: =IF(ISNUMBER($E15),F15+14,"") | H15: =IF(ISNUMBER($E15),G15+14,"") | I15: =IF(ISNUMBER($E15),H15+14,"") | J15: =IF(NOT(ISNUMBER($E15)),"",IF($E15>=F15,"Done",F15-TODAY())) | K15: =IF(NOT(ISNUMBER($E15)),"",IF($E15>=G15,"Done",G15-TODAY())) | L15: =IF(NOT(ISNUMBER($E15)),"",IF($E15>=H15,"Done",H15-TODAY())) | M15: =IF(NOT(ISNUMBER($E15)),"",IF($E15>=I15,"Done",I15-TODAY()))
A16: Advent | B16: =IF(COUNTIF('PE names final'!A:A, A16)+COUNTIF('PE porfolio names final'!A:A,A16)=1, "Yes", "Error") -> Yes | C16: {=_xlfn.IFS(AND(COUNTIF('PE names final'!A:A,A16)>0,COUNTIF('PE porfolio names final'!A:A,A16)>0),"PE & Portfolio",COUNTIF('PE names final'!A:A,A16)>0,"PE",COUNTIF('PE porfolio names final'!A:A,A16)>0,"Portfolio",TRUE,"")} -> PE | D16: =_xlfn.LET(_xlpm.L,IFERROR(_xlfn.XLOOKUP(A16,'PE names final'!A:A,'PE names final'!C:C),_xlfn.XLOOKUP(A16,'PE porfolio names final'!A:A,'PE porfolio names final'!C:C,"")),IF(_xlpm.L=0,"",_xlpm.L)) -> 46035 | E16: =_xlfn.LET(_xlpm.d,IFERROR(_xlfn.XLOOKUP(A16,'PE names final'!A:A,'PE names final'!D:D),_xlfn.XLOOKUP(A16,'PE porfolio names final'!A:A,'PE porfolio names final'!D:D,"")),IF(_xlpm.d=0,"",IF(_xlpm.d<D16,"Error",_xlpm.d))) -> 46091 | F16: =IF(ISNUMBER($E16),D16+14,"") -> 46049 | G16: =IF(ISNUMBER($E16),F16+14,"") -> 46063 | H16: =IF(ISNUMBER($E16),G16+14,"") -> 46077 | I16: =IF(ISNUMBER($E16),H16+14,"") -> 46091 | J16: =IF(NOT(ISNUMBER($E16)),"",IF($E16>=F16,"Done",F16-TODAY())) -> Done | K16: =IF(NOT(ISNUMBER($E16)),"",IF($E16>=G16,"Done",G16-TODAY())) -> Done | L16: =IF(NOT(ISNUMBER($E16)),"",IF($E16>=H16,"Done",H16-TODAY())) -> Done | M16: =IF(NOT(ISNUMBER($E16)),"",IF($E16>=I16,"Done",I16-TODAY())) -> Done
A17: Kedaara | B17: =IF(COUNTIF('PE names final'!A:A, A17)+COUNTIF('PE porfolio names final'!A:A,A17)=1, "Yes", "Error") -> Yes | C17: {=_xlfn.IFS(AND(COUNTIF('PE names final'!A:A,A17)>0,COUNTIF('PE porfolio names final'!A:A,A17)>0),"PE & Portfolio",COUNTIF('PE names final'!A:A,A17)>0,"PE",COUNTIF('PE porfolio names final'!A:A,A17)>0,"Portfolio",TRUE,"")} -> PE | D17: =_xlfn.LET(_xlpm.L,IFERROR(_xlfn.XLOOKUP(A17,'PE names final'!A:A,'PE names final'!C:C),_xlfn.XLOOKUP(A17,'PE porfolio names final'!A:A,'PE porfolio names final'!C:C,"")),IF(_xlpm.L=0,"",_xlpm.L)) -> 46034 | E17: =_xlfn.LET(_xlpm.d,IFERROR(_xlfn.XLOOKUP(A17,'PE names final'!A:A,'PE names final'!D:D),_xlfn.XLOOKUP(A17,'PE porfolio names final'!A:A,'PE porfolio names final'!D:D,"")),IF(_xlpm.d=0,"",IF(_xlpm.d<D17,"Error",_xlpm.d))) -> Got response | F17: =IF(ISNUMBER($E17),D17+14,"") | G17: =IF(ISNUMBER($E17),F17+14,"") | H17: =IF(ISNUMBER($E17),G17+14,"") | I17: =IF(ISNUMBER($E17),H17+14,"") | J17: =IF(NOT(ISNUMBER($E17)),"",IF($E17>=F17,"Done",F17-TODAY())) | K17: =IF(NOT(ISNUMBER($E17)),"",IF($E17>=G17,"Done",G17-TODAY())) | L17: =IF(NOT(ISNUMBER($E17)),"",IF($E17>=H17,"Done",H17-TODAY())) | M17: =IF(NOT(ISNUMBER($E17)),"",IF($E17>=I17,"Done",I17-TODAY()))
A18: 8 Roads | B18: =IF(COUNTIF('PE names final'!A:A, A18)+COUNTIF('PE porfolio names final'!A:A,A18)=1, "Yes", "Error") -> Yes | C18: {=_xlfn.IFS(AND(COUNTIF('PE names final'!A:A,A18)>0,COUNTIF('PE porfolio names final'!A:A,A18)>0),"PE & Portfolio",COUNTIF('PE names final'!A:A,A18)>0,"PE",COUNTIF('PE porfolio names final'!A:A,A18)>0,"Portfolio",TRUE,"")} -> PE | D18: =_xlfn.LET(_xlpm.L,IFERROR(_xlfn.XLOOKUP(A18,'PE names final'!A:A,'PE names final'!C:C),_xlfn.XLOOKUP(A18,'PE porfolio names final'!A:A,'PE porfolio names final'!C:C,"")),IF(_xlpm.L=0,"",_xlpm.L)) -> 46055 | E18: =_xlfn.LET(_xlpm.d,IFERROR(_xlfn.XLOOKUP(A18,'PE names final'!A:A,'PE names final'!D:D),_xlfn.XLOOKUP(A18,'PE porfolio names final'!A:A,'PE porfolio names final'!D:D,"")),IF(_xlpm.d=0,"",IF(_xlpm.d<D18,"Error",_xlpm.d))) -> 46111 | F18: =IF(ISNUMBER($E18),D18+14,"") -> 46069 | G18: =IF(ISNUMBER($E18),F18+14,"") -> 46083 | H18: =IF(ISNUMBER($E18),G18+14,"") -> 46097 | I18: =IF(ISNUMBER($E18),H18+14,"") -> 46111 | J18: =IF(NOT(ISNUMBER($E18)),"",IF($E18>=F18,"Done",F18-TODAY())) -> Done | K18: =IF(NOT(ISNUMBER($E18)),"",IF($E18>=G18,"Done",G18-TODAY())) -> Done | L18: =IF(NOT(ISNUMBER($E18)),"",IF($E18>=H18,"Done",H18-TODAY())) -> Done | M18: =IF(NOT(ISNUMBER($E18)),"",IF($E18>=I18,"Done",I18-TODAY())) -> Done
A19: Convergent Finance | B19: =IF(COUNTIF('PE names final'!A:A, A19)+COUNTIF('PE porfolio names final'!A:A,A19)=1, "Yes", "Error") -> Yes | C19: {=_xlfn.IFS(AND(COUNTIF('PE names final'!A:A,A19)>0,COUNTIF('PE porfolio names final'!A:A,A19)>0),"PE & Portfolio",COUNTIF('PE names final'!A:A,A19)>0,"PE",COUNTIF('PE porfolio names final'!A:A,A19)>0,"Portfolio",TRUE,"")} -> PE | D19: =_xlfn.LET(_xlpm.L,IFERROR(_xlfn.XLOOKUP(A19,'PE names final'!A:A,'PE names final'!C:C),_xlfn.XLOOKUP(A19,'PE porfolio names final'!A:A,'PE porfolio names final'!C:C,"")),IF(_xlpm.L=0,"",_xlpm.L)) -> 46034 | E19: =_xlfn.LET(_xlpm.d,IFERROR(_xlfn.XLOOKUP(A19,'PE names final'!A:A,'PE names final'!D:D),_xlfn.XLOOKUP(A19,'PE porfolio names final'!A:A,'PE porfolio names final'!D:D,"")),IF(_xlpm.d=0,"",IF(_xlpm.d<D19,"Error",_xlpm.d))) -> 46091 | F19: =IF(ISNUMBER($E19),D19+14,"") -> 46048 | G19: =IF(ISNUMBER($E19),F19+14,"") -> 46062 | H19: =IF(ISNUMBER($E19),G19+14,"") -> 46076 | I19: =IF(ISNUMBER($E19),H19+14,"") -> 46090 | J19: =IF(NOT(ISNUMBER($E19)),"",IF($E19>=F19,"Done",F19-TODAY())) -> Done | K19: =IF(NOT(ISNUMBER($E19)),"",IF($E19>=G19,"Done",G19-TODAY())) -> Done | L19: =IF(NOT(ISNUMBER($E19)),"",IF($E19>=H19,"Done",H19-TODAY())) -> Done | M19: =IF(NOT(ISNUMBER($E19)),"",IF($E19>=I19,"Done",I19-TODAY())) -> Done
... A136: In2IT Technologies | B136: =IF(COUNTIF('PE names final'!A:A, A136)+COUNTIF('PE porfolio names final'!A:A,A136)=1, "Yes", "Error") -> Yes | C136: {=_xlfn.IFS(AND(COUNTIF('PE names final'!A:A,A136)>0,COUNTIF('PE porfolio names final'!A:A,A136)>0),"PE & Portfolio",COUNTIF('PE names final'!A:A,A136)>0,"PE",COUNTIF('PE porfolio names final'!A:A,A136)>0,"Portfolio",TRUE,"")} -> Portfolio | D136: =_xlfn.LET(_xlpm.L,IFERROR(_xlfn.XLOOKUP(A136,'PE names final'!A:A,'PE names final'!C:C),_xlfn.XLOOKUP(A136,'PE porfolio names final'!A:A,'PE porfolio names final'!C:C,"")),IF(_xlpm.L=0,"",_xlpm.L)) -> 46163 | E136: =_xlfn.LET(_xlpm.d,IFERROR(_xlfn.XLOOKUP(A136,'PE names final'!A:A,'PE names final'!D:D),_xlfn.XLOOKUP(A136,'PE porfolio names final'!A:A,'PE porfolio names final'!D:D,"")),IF(_xlpm.d=0,"",IF(_xlpm.d<D136,"Error",_xlpm.d))) -> Got response | F136: =IF(ISNUMBER($E136),D136+14,"") | G136: =IF(ISNUMBER($E136),F136+14,"") | H136: =IF(ISNUMBER($E136),G136+14,"") | I136: =IF(ISNUMBER($E136),H136+14,"") | J136: =IF(NOT(ISNUMBER($E136)),"",IF($E136>=F136,"Done",F136-TODAY())) | K136: =IF(NOT(ISNUMBER($E136)),"",IF($E136>=G136,"Done",G136-TODAY())) | L136: =IF(NOT(ISNUMBER($E136)),"",IF($E136>=H136,"Done",H136-TODAY())) | M136: =IF(NOT(ISNUMBER($E136)),"",IF($E136>=I136,"Done",I136-TODAY()))

Sheet Additional >>>

Sheet Remaining PE companies
B1: Remaining private equity buyers - 22by7
A4: S.No. | B4: Company name | C4: HQ | D4: Website | E4: Bucket | F4: Notes
A5: 1 | B5: 8 Roads | C5: Bermuda | D5: https://eightroads.com/en/ | E5: Foreign PE with potfolio companies not having Indian offices
A6: 2 | B6: Advent | C6: United States | D6: https://www.adventinternational.com/ | E6: Foreign PE with potfolio companies not having Indian offices
A7: 3 | B7: Affirma Capital | C7: Singapore | D7: https://affirmacapital.com/ | E7: Foreign PE with potfolio companies not having Indian offices | F7: Relevant investments like Redington
A8: 4 | B8: Arlington Capital Partners | C8: USA | D8: https://arlingtoncap.com/ | E8: Foreign PE with potfolio companies not having Indian offices
A9: 5 | B9: Ascent Capital | C9: India | D9: https://ascentcapital.in/ | E9: Indian PEs with unrelated potfolio companies | F9: No direct investments but notable ones like Acko and Big Basket
A10: 6 | B10: Avataar Ventures | C10: India | D10: https://www.avataar.vc/ | E10: Indian PEs with unrelated potfolio companies | F10: No directly relevant investments; Safe (cybersecurity platform) scaled internationally
A11: 7 | B11: BGF | C11: UK | D11: https://www.bgf.co.uk/ | E11: Foreign PE with potfolio companies not having Indian offices | F11: UK based but highly relevant investments
A12: 8 | B12: Blue Alliance | C12: USA | D12: https://www.bluealliance.com/ | E12: Foreign PE with potfolio companies not having Indian offices
A13: 9 | B13: ChrysCapital | C13: Mauritius | D13: https://chryscapital.com/ | E13: Foreign PE with potfolio companies not having Indian offices
A14: 10 | B14: Convergent Finance | C14: India | D14: https://convergentfinance.com/ | E14: Indian PEs with unrelated potfolio companies | F14: No direct investments but notable ones like Onward Technologies in software and Thomas Cook (India)
A15: 11 | B15: Creador | C15: Malysia | D15: https://creador.com/ | E15: Foreign PE with potfolio companies not having Indian offices
A16: 28 | B16: Evergreen Services Group | C16: USA | D16: https://www.evergreensg.com/ | E16: Foreign PE with potfolio companies not having Indian offices
A17: 12 | B17: Gaja Capital | C17: India | D17: https://gajacapital.com/ | E17: Indian PEs with unrelated potfolio companies | F17: No direct investments but notable ones like Fractal Analytics in software and Avendus
A18: 13 | B18: Great Hill Partners | C18: USA | D18: https://www.greathillpartners.com/ | E18: Foreign PE with potfolio companies not having Indian offices | F18: Numerous prior relevant investments
A19: 14 | B19: Halyard Capital | C19: USA | D19: https://www.halyard.com/ | E19: Foreign PE with potfolio companies not having Indian offices
A20: 15 | B20: Investcorp | C20: Bahrain | D20: https://www.investcorp.com/ | E20: Indian PEs with unrelated potfolio companies | F20: Mid-market investments is India as well as Europe and the USA
A21: 16 | B21: Kedaara | C21: India | D21: https://kedaara.com/ | E21: Indian PEs with unrelated potfolio companies | F21: No directly relevant investments; Impetus and Neurealm (cybersecurity platform) - scaled internationally
A22: 17 | B22: Navis Capital Partners | C22: Malysia | D22: https://www.naviscapital.com/ | E22: Foreign PE with potfolio companies not having Indian offices
A23: 18 | B23: Petros Partners | C23: USA | D23: https://www.petrospartners.com/ | E23: Foreign PE with potfolio companies not having Indian offices
A24: 19 | B24: Premji Invest | C24: India | D24: https://in.premjiinvest.com/ | E24: Indian PEs with unrelated potfolio companies | F24: No direct investments but notable investments in software with potential to scale abroad
A25: 20 | B25: Prosperity7 Ventures | C25: Saudi Arabia | D25: https://www.prosperity7vc.com/ | E25: Foreign PE with potfolio companies not having Indian offices
A26: 21 | B26: Runtide Capital | C26: USA | D26: https://www.runtidecapital.com/ | E26: Foreign PE with potfolio companies not having Indian offices
A27: 22 | B27: Samara Capital | C27: India | D27: https://samaracapital.com/ | E27: Indian PEs with unrelated potfolio companies | F27: No direct investments but notable ones like First Meridian and SMS
A28: 23 | B28: Stakeboat Capital | C28: India | D28: https://stakeboat.com/ | E28: Indian PEs with unrelated potfolio companies | F28: No direct investments but notable ones like Ozonotel (software) - scaled internationally
A29: 24 | B29: Steadview Capital | C29: UK | D29: https://www.steadview.com/ | E29: Foreign PE with potfolio companies not having Indian offices
A30: 25 | B30: Sunstone Partners | C30: USA | D30: https://sunstonepartners.com/ | E30: Foreign PE with potfolio companies not having Indian offices
A31: 26 | B31: Transom Capital | C31: USA | D31: https://transomcap.com/ | E31: Foreign PE with potfolio companies not having Indian offices
A32: 27 | B32: Westbridge Capital | C32: India | D32: https://westbridgecap.com/ | E32: Indian PEs with unrelated potfolio companies | F32: No directly relevant investments; Invests in leading businesses and Indian brands (Mindtree, Cognizant, etc.) - scaling internationally

Sheet PE summary analysis
A3: Holding company | B3: Repetitions | E3: Holding company | F3: Repetitions | I3: Holding company | J3: Expand Indian presence | K3: Expand Asian presence | L3: Offshore/onshore expansion | M3: Total
A4: Abry Partners | B4: =COUNTIF('PE porfolio names final'!$R:$R,'PE summary analysis'!$A4) -> 2 | E4: MC Partners | F4: =_xlfn.XLOOKUP(E4,A:A,B:B) -> 5 | I4: MC Partners | J4: =COUNTIFS('PE porfolio names final'!$R:$R,$I4,'PE porfolio names final'!$T:$T,J$3) -> 1 | K4: =COUNTIFS('PE porfolio names final'!$R:$R,$I4,'PE porfolio names final'!$T:$T,K$3) -> 1 | L4: =COUNTIFS('PE porfolio names final'!$R:$R,$I4,'PE porfolio names final'!$T:$T,L$3) -> 3 | M4: =SUM(J4:L4) -> 5
A5: Agellus Capital | B5: =COUNTIF('PE porfolio names final'!$R:$R,'PE summary analysis'!$A5) -> 1 | E5: Abry Partners | F5: =_xlfn.XLOOKUP(E5,A:A,B:B) -> 2 | I5: Abry Partners | J5: =COUNTIFS('PE porfolio names final'!$R:$R,$I5,'PE porfolio names final'!$T:$T,J$3) -> 1 | K5: =COUNTIFS('PE porfolio names final'!$R:$R,$I5,'PE porfolio names final'!$T:$T,K$3) -> 0 | L5: =COUNTIFS('PE porfolio names final'!$R:$R,$I5,'PE porfolio names final'!$T:$T,L$3) -> 1 | M5: =SUM(J5:L5) -> 2
A6: Atlantic Street Capital | B6: =COUNTIF('PE porfolio names final'!$R:$R,'PE summary analysis'!$A6) -> 1 | E6: Bregal Sagemount | F6: =_xlfn.XLOOKUP(E6,A:A,B:B) -> 2 | I6: Bregal Sagemount | J6: =COUNTIFS('PE porfolio names final'!$R:$R,$I6,'PE porfolio names final'!$T:$T,J$3) -> 0 | K6: =COUNTIFS('PE porfolio names final'!$R:$R,$I6,'PE porfolio names final'!$T:$T,K$3) -> 0 | L6: =COUNTIFS('PE porfolio names final'!$R:$R,$I6,'PE porfolio names final'!$T:$T,L$3) -> 2 | M6: =SUM(J6:L6) -> 2
A7: Bregal Sagemount | B7: =COUNTIF('PE porfolio names final'!$R:$R,'PE summary analysis'!$A7) -> 2 | E7: Frontenac | F7: =_xlfn.XLOOKUP(E7,A:A,B:B) -> 2 | I7: Frontenac | J7: =COUNTIFS('PE porfolio names final'!$R:$R,$I7,'PE porfolio names final'!$T:$T,J$3) -> 0 | K7: =COUNTIFS('PE porfolio names final'!$R:$R,$I7,'PE porfolio names final'!$T:$T,K$3) -> 0 | L7: =COUNTIFS('PE porfolio names final'!$R:$R,$I7,'PE porfolio names final'!$T:$T,L$3) -> 2 | M7: =SUM(J7:L7) -> 2
A8: Court Square | B8: =COUNTIF('PE porfolio names final'!$R:$R,'PE summary analysis'!$A8) -> 1 | E8: Fulcrum IT partners | F8: =_xlfn.XLOOKUP(E8,A:A,B:B) -> 2 | I8: Fulcrum IT partners | J8: =COUNTIFS('PE porfolio names final'!$R:$R,$I8,'PE porfolio names final'!$T:$T,J$3) -> 0 | K8: =COUNTIFS('PE porfolio names final'!$R:$R,$I8,'PE porfolio names final'!$T:$T,K$3) -> 0 | L8: =COUNTIFS('PE porfolio names final'!$R:$R,$I8,'PE porfolio names final'!$T:$T,L$3) -> 2 | M8: =SUM(J8:L8) -> 2
A9: FFL Group | B9: =COUNTIF('PE porfolio names final'!$R:$R,'PE summary analysis'!$A9) -> 1 | E9: HIG Capital | F9: =_xlfn.XLOOKUP(E9,A:A,B:B) -> 2 | I9: HIG Capital | J9: =COUNTIFS('PE porfolio names final'!$R:$R,$I9,'PE porfolio names final'!$T:$T,J$3) -> 0 | K9: =COUNTIFS('PE porfolio names final'!$R:$R,$I9,'PE porfolio names final'!$T:$T,K$3) -> 0 | L9: =COUNTIFS('PE porfolio names final'!$R:$R,$I9,'PE porfolio names final'!$T:$T,L$3) -> 2 | M9: =SUM(J9:L9) -> 2
A10: Frontenac | B10: =COUNTIF('PE porfolio names final'!$R:$R,'PE summary analysis'!$A10) -> 2 | E10: Oval Partners | F10: =_xlfn.XLOOKUP(E10,A:A,B:B) -> 1 | I10: Oval Partners | J10: =COUNTIFS('PE porfolio names final'!$R:$R,$I10,'PE porfolio names final'!$T:$T,J$3) -> 0 | K10: =COUNTIFS('PE porfolio names final'!$R:$R,$I10,'PE porfolio names final'!$T:$T,K$3) -> 0 | L10: =COUNTIFS('PE porfolio names final'!$R:$R,$I10,'PE porfolio names final'!$T:$T,L$3) -> 1 | M10: =SUM(J10:L10) -> 1
A11: Fulcrum IT partners | B11: =COUNTIF('PE porfolio names final'!$R:$R,'PE summary analysis'!$A11) -> 2 | E11: Recognize | F11: =_xlfn.XLOOKUP(E11,A:A,B:B) -> 2 | I11: Recognize | J11: =COUNTIFS('PE porfolio names final'!$R:$R,$I11,'PE porfolio names final'!$T:$T,J$3) -> 1 | K11: =COUNTIFS('PE porfolio names final'!$R:$R,$I11,'PE porfolio names final'!$T:$T,K$3) -> 0 | L11: =COUNTIFS('PE porfolio names final'!$R:$R,$I11,'PE porfolio names final'!$T:$T,L$3) -> 1 | M11: =SUM(J11:L11) -> 2
A12: HCAP Partners | B12: =COUNTIF('PE porfolio names final'!$R:$R,'PE summary analysis'!$A12) -> 1 | E12: Agellus Capital | F12: =_xlfn.XLOOKUP(E12,A:A,B:B) -> 1 | I12: Agellus Capital | J12: =COUNTIFS('PE porfolio names final'!$R:$R,$I12,'PE porfolio names final'!$T:$T,J$3) -> 0 | K12: =COUNTIFS('PE porfolio names final'!$R:$R,$I12,'PE porfolio names final'!$T:$T,K$3) -> 0 | L12: =COUNTIFS('PE porfolio names final'!$R:$R,$I12,'PE porfolio names final'!$T:$T,L$3) -> 1 | M12: =SUM(J12:L12) -> 1
A13: HIG Capital | B13: =COUNTIF('PE porfolio names final'!$R:$R,'PE summary analysis'!$A13) -> 2 | E13: Atlantic Street Capital | F13: =_xlfn.XLOOKUP(E13,A:A,B:B) -> 1 | I13: Atlantic Street Capital | J13: =COUNTIFS('PE porfolio names final'!$R:$R,$I13,'PE porfolio names final'!$T:$T,J$3) -> 0 | K13: =COUNTIFS('PE porfolio names final'!$R:$R,$I13,'PE porfolio names final'!$T:$T,K$3) -> 0 | L13: =COUNTIFS('PE porfolio names final'!$R:$R,$I13,'PE porfolio names final'!$T:$T,L$3) -> 1 | M13: =SUM(J13:L13) -> 1
A14: Insight Partners | B14: =COUNTIF('PE porfolio names final'!$R:$R,'PE summary analysis'!$A14) -> 1 | E14: Court Square | F14: =_xlfn.XLOOKUP(E14,A:A,B:B) -> 1 | I14: Court Square | J14: =COUNTIFS('PE porfolio names final'!$R:$R,$I14,'PE porfolio names final'!$T:$T,J$3) -> 0 | K14: =COUNTIFS('PE porfolio names final'!$R:$R,$I14,'PE porfolio names final'!$T:$T,K$3) -> 0 | L14: =COUNTIFS('PE porfolio names final'!$R:$R,$I14,'PE porfolio names final'!$T:$T,L$3) -> 1 | M14: =SUM(J14:L14) -> 1
A15: Intel Capital | B15: =COUNTIF('PE porfolio names final'!$R:$R,'PE summary analysis'!$A15) -> 1 | E15: FFL Group | F15: =_xlfn.XLOOKUP(E15,A:A,B:B) -> 1 | I15: FFL Group | J15: =COUNTIFS('PE porfolio names final'!$R:$R,$I15,'PE porfolio names final'!$T:$T,J$3) -> 0 | K15: =COUNTIFS('PE porfolio names final'!$R:$R,$I15,'PE porfolio names final'!$T:$T,K$3) -> 0 | L15: =COUNTIFS('PE porfolio names final'!$R:$R,$I15,'PE porfolio names final'!$T:$T,L$3) -> 1 | M15: =SUM(J15:L15) -> 1
... A37: VSS Capital Partners | B37: =COUNTIF('PE porfolio names final'!$R:$R,'PE summary analysis'!$A37) -> 1 | E37: VSS Capital Partners | F37: =_xlfn.XLOOKUP(E37,A:A,B:B) -> 1 | I37: VSS Capital Partners | J37: =COUNTIFS('PE porfolio names final'!$R:$R,$I37,'PE porfolio names final'!$T:$T,J$3) -> 1 | K37: =COUNTIFS('PE porfolio names final'!$R:$R,$I37,'PE porfolio names final'!$T:$T,K$3) -> 0 | L37: =COUNTIFS('PE porfolio names final'!$R:$R,$I37,'PE porfolio names final'!$T:$T,L$3) -> 0 | M37: =SUM(J37:L37) -> 1
I38: Total | J38: =SUM(J4:J37) -> 9 | K38: =SUM(K4:K37) -> 1 | L38: =SUM(L4:L37) -> 34 | M38: =SUM(M4:M37) -> 44

Sheet PE names
A1: Private equity buyers - 22by7
B3: =SUBTOTAL(3,B4:B1048576) -> 63
A4: S.No. | B4: Company name | C4: HQ | D4: Cheque size | E4: Porfolio companies | F4: Deal rationale | G4: Website | H4: Status | I4: Next Follow-up Date | J4: Contact Name | K4: Designation | L4: Email Id | M4: Linkedin
A5: 1 | B5: Trunorth | C5: India | D5: N/A / mid market | E5: Accion labs, iLink Digital | F5: Relevent prior investments seem to be large in size in comparison the 22by7; prior investments have taken a stance in the US | G5: https://www.truenorth.co.in/ | J5: Mahinder Singh Juneja | K5: Partner | L5: maninder@truenorth.co.in | M5: https://www.linkedin.com/in/maninder-singh-juneja-35a01a13/
A6: =A5+1 -> 2 | B6: Advent | C6: USA | D6: $50m - $2b (Advent Tech II Fund) | E6: Tredence | F6: Relevant prior invrstments, however ticket sizes may be seen as too large | G6: https://www.adventinternational.com/ | J6: Mohammed Anjarwala | K6: Partner | L6: manjarwala@adventinternational.com | M6: https://www.linkedin.com/in/anjarwala/
A7: =A6+1 -> 3 | B7: Kedaara | C7: India | D7: N/A | E7: Impetus, Neurealm | F7: Relevent prior investments seem to be large in size in comparison the 22by7; prior investments have taken a stance in the US | G7: https://kedaara.com/ | J7: Manish Kejriwal | K7: Founder/Managing Partner | L7: manish.kejriwal@kedaara.com | M7: https://www.linkedin.com/in/manish-kejriwal-1a7336/
A8: =A7+1 -> 4 | B8: 8 Roads | C8: Bermuda | D8: N/A | E8: Safe, Whatfix | F8: From precedent transactions | G8: https://eightroads.com/en/ | J8: Gordon Zhang | K8: Partner | L8: gordon.zhang@eightroads.com | M8: https://www.linkedin.com/in/gordon-zhang-9490b3273/
A9: =A8+1 -> 5 | B9: Convergent Finance | C9: India | D9: N/A | E9: Onward Technologies | F9: HIGHLY RELEVANT; From precedent transactions | G9: https://convergentfinance.com/ | J9: Harsha Raghavan | K9: Managing Partner | L9: harsha@convergentfinance.com | M9: https://www.linkedin.com/in/harsha-raghavan-1218a11b5/
A10: =A9+1 -> 6 | B10: Premji Invest | C10: India | D10: N/A | E10: Increff, Lambda Test | F10: Close investments in businesses that utlise cloud services | G10: https://in.premjiinvest.com/ | J10: Kaveesh Chawla | K10: Partner | L10: kaveesh.chawla@premjiinvest.com | M10: https://www.linkedin.com/in/kaveeshchawla/
A11: =A10+1 -> 7 | B11: Insight Partners | C11: USA | D11: N/A / mid market | E11: Kaseya | F11: Relevant prior investments, however, none that are relevant in India; Indian investments include Apna and BhartPe; portfolio companies may be too large in comparision to 22by7 | G11: https://www.insightpartners.com/ | J11: Thilo Semmelbauer | K11: Managing Director | L11: tsemmelbauer@insightpartners.com | M11: https://www.linkedin.com/in/thilo/
A12: =A11+1 -> 8 | B12: Samara Capital | C12: India | D12: N/A / mid market | E12: Iron Mountain | F12: Relevent prior investments seem to be large in size in comparison the 22by7; prior investments have taken a stance in the US | G12: https://samaracapital.com/ | J12: Manish Mehta | K12: Managing Director | L12: manish@samaracapital.com | M12: https://www.linkedin.com/in/manish-mehta-0883873/
A13: =A12+1 -> 9 | B13: Frontenac | C13: USA | D13: $50m-$150m | E13: Ideal Integrations | F13: Relevant prior investments, however criteria includes North America based - can fund 22by7 for acquisitions in North America | G13: https://frontenac.com/ | H13: Emailed | J13: Walter Florence | K13: Managing Partner | L13: wflorence@frontenac.com | M13: https://www.linkedin.com/in/walterflorence/
A14: =A13+1 -> 10 | B14: PSP Partners | C14: USA | D14: N/A | E14: Ntiva | F14: Relevant prior investments, however, none in India; mentions that the PE is an international investment firm so potential to invest in 22by7 | G14: https://www.psppartners.com/ | H14: Emailed | J14: Jon Skinner | K14: CEO | L14: jskinner@psppartners.com | M14: https://www.linkedin.com/in/jon-skinner-50a4422/
A15: =A14+1 -> 11 | B15: Newspring Holdings | C15: USA | D15: $1m-$10m EBITDA | E15: Magna5 | F15: Relevant prior investments, however, none in India; might be interested to invest in 22by7 if it plans on acquiring US based companies | G15: https://newspringcapital.com/ | H15: Emailed | J15: Greg Barger | K15: General Partner | L15: gbarger@newspringcapital.com | M15: https://www.linkedin.com/in/greg-barger-172b0617/
A16: =A15+1 -> 12 | B16: FFL Group | C16: USA | D16: N/A | E16: Abacus Group | F16: From precedent transactions | G16: https://fflpartners.com/ | H16: Emailed | J16: Chris Harris | K16: Managing Partner | L16: charris@fflpartners.com | M16: https://www.linkedin.com/in/chris-harris-1b730a6/
A17: =A16+1 -> 13 | B17: Evergreen Services Group | C17: USA | D17: N/A | E17: N/A | F17: From precedent transactions as they mention that they invest in tech enabled businesses | G17: https://www.evergreensg.com/ | H17: Got response | I17: NA | J17: Ramsey Sahyoun | K17: Co-founder/M&A Partner | L17: rsahyoun@evergreensg.com | M17: https://www.linkedin.com/in/ramsey-sahyoun-67b32683/
A18: =A17+1 -> 14 | B18: Agellus Capital | C18: USA | D18: $2m-$25m EBITDA | E18: Compass MSP | F18: From precedent transactions | G18: https://www.agellus.com/ | H18: Emailed | J18: Jeff Aiello | K18: Co-founder/Managing Partner | L18: jaiello@agellus.com | M18: https://www.linkedin.com/in/jeffaiello/
A19: =A18+1 -> 15 | B19: Creador | C19: Malysia | D19: N/A | E19: Hinduja Tech, IVALUE | F19: From precedent transactions; have invested in many Indian companies | G19: https://creador.com/ | J19: Alberto Lazzari | K19: PE Professional | L19: a.lazzari@creador.com | M19: https://www.linkedin.com/in/alberto-lazzari-mba-217b944a/
A20: =A19+1 -> 16 | B20: Sunstone Partners | C20: USA | D20: N/A | E20: KMS Technology | F20: From precedent transactions | G20: https://sunstonepartners.com/ | H20: Got response | I20: NA | J20: Ankur Rathi | K20: Partner | L20: arathi@sunstonepartners.com | M20: https://www.linkedin.com/in/arathi2/
A21: =A20+1 -> 17 | B21: ChrysCapital | C21: Mauritius | D21: N/A | E21: Xoriant | F21: Although they probably invest in large ticket sizes, they have relevant prior Indian investments which have scaled in the US (Xoriant) | G21: https://chryscapital.com/ | J21: Sanjiv Kaul | K21: Partner | L21: sanjiv@chryscapital.com | M21: https://www.linkedin.com/in/sanjiv-kaul-135b301a5/
A22: =A21+1 -> 18 | B22: Halyard Capital | C22: USA | D22: N/A / mid market | E22: Inflow Group | F22: From precedent transactions | G22: https://www.halyard.com/ | H22: Emailed | J22: Robert Nolan | K22: Managing Partner | L22: rnolan@halyard.com | M22: https://www.linkedin.com/in/robert-nolan10/
A23: =A22+1 -> 19 | B23: Virtuvian Partners | C23: UK | D23: N/A | E23: Meriplex | F23: Although they probably invest in large ticket sizes, they have relevant prior investments which have scaled in the US and have offices in India | G23: https://www.vitruvianpartners.com/ | J23: Joe O'Mara | K23: Partner | L23: joe.omara@vitruvianpartners.com | M23: https://www.linkedin.com/in/joe-o-mara-7822073/
A24: =A23+1 -> 20 | B24: MC Partners | C24: USA | D24: N/A | E24: Ascend Technologies | F24: From Precedent transactions | G24: https://www.mcpartners.com/ | H24: Emailed | J24: Ryan Carr | K24: Partner | L24: rcarr@mcpartners.com | M24: https://www.linkedin.com/in/ryan-carr-b6453736/
A25: =A24+1 -> 21 | B25: HIG Capital | C25: USA | D25: N/A | E25: ECI | F25: From precent transactions and they also have an office in Asia and strong presence in the Americas - might be willing to back 22by7 | G25: https://hig.com/ | H25: Emailed | J25: Micael Hagelin | K25: Managing Director | L25: mhagelin@higcapital.com | M25: https://www.linkedin.com/in/micael-hagelin-a9a85a/
A26: =A25+1 -> 22 | B26: Bregal Sagemount | C26: USA | D26: $20m-$400m | E26: Congruity 360 | F26: From precedent transactions and have a stong American presence | G26: https://www.sagemount.com/ | H26: Emailed | J26: Michael Kosty | K26: Co-founder/Partner | L26: michael.kosty@sagemount.com | M26: https://www.linkedin.com/in/kostymichael/
A27: =A26+1 -> 23 | B27: Navis Capital Partners | C27: Malysia | D27: N/A / mid market | E27: Software Combined | F27: From precedent transactions; strong Asian presence; Indian investments | G27: https://www.naviscapital.com/ | J27: Gordon C. | K27: Operating Partner | L27: gchan@naviscapital.com | M27: https://www.linkedin.com/in/gordon-c-2118734/
A28: =A27+1 -> 24 | B28: Ascent Capital | C28: India | D28: N/A | E28: Skanray | F28: Although limited portfolio companies and unrelated precedent transactions, has a presence in India and potential to scale internationally | G28: https://ascentcapital.in/ | J28: Raja Kumar | K28: Founder/Managing Partner | L28: raja@ascentcapital.in | M28: https://www.linkedin.com/in/raja-kumar-455b7245/
A29: =A28+1 -> 25 | B29: Gaja Capital | C29: India | D29: N/A | E29: Fractal Analytics | F29: Although limited portfolio companies and unrelated precedent transactions, has a presence in India and potential to scale internationally | G29: https://gajacapital.com/ | J29: Sushane Chopra | K29: Partner | L29: sushane.chopra@gajacapital.com | M29: https://www.linkedin.com/in/sushane-chopra-b248334/
A30: =A29+1 -> 26 | B30: Westbridge Capital | C30: India | D30: N/A | E30: Infotech | F30: Although ticket sizes may be large, seen to be investing in technology services and scaling internationally | G30: https://westbridgecap.com/ | J30: Sumir Chadha | K30: Co-founder/Managing Partner | L30: sumir.chadha@westbridgecap.com | M30: https://www.linkedin.com/in/sumir-chadha-bb8b563/
A31: =A30+1 -> 27 | B31: Norwest | C31: USA | D31: N/A | E31: Celebal Technologies | F31: Although ticket sizes may be large, there are relevant Indian investments, offices worldwide (including India) - potential to scale internationally | G31: https://www.norwest.com/ | H31: Emailed | J31: Jon Kossow | K31: Managing Partner | L31: jkossow@nvp.com | M31: https://www.linkedin.com/in/jon-kossow-42706b2/
A32: =A31+1 -> 28 | B32: Stakeboat Capital | C32: India | D32: N/A / mid market | E32: Ferfier Technologies | F32: Although no directly relevant investments - still cloud based - potential to scale internationally | G32: https://stakeboat.com/ | J32: Chandrasekar Kandasamy | K32: Managing Partner | L32: chandra@stakeboat.com | M32: https://www.linkedin.com/in/chandrasekar-kandasamy-4b8703/
A33: =A32+1 -> 29 | B33: Intel Capital | C33: USA | D33: N/A | E33: NxtGen | F33: HIGHLY RELEVANT - revelvant portfolio companies (including an Indian name) - seems to have worldwide presence, potential to scale internationally | G33: https://www.intelcapital.com/ | H33: Emailed | J33: Aravind Bharadwaj | K33: Investment Partner | L33: aravind.bharadwaj@intel.com | M33: https://www.linkedin.com/in/aravindbharadwaj/
A34: =A33+1 -> 30 | B34: Prosperity7 Ventures | C34: Saudi Arabia | D34: N/A | E34: Appomni | F34: Although it’s a VC, backed by Aramco and has multiple investments in cloud/cybersecurity related companies; deep Asian expertise | G34: https://www.prosperity7vc.com/ | J34: Abhishek Shukla | K34: Managing Director and Head of North America | L34: abhishek.shukla@p7vc.com | M34: https://www.linkedin.com/in/ashukla1/
A35: =A34+1 -> 31 | B35: Steadview Capital | C35: UK | D35: N/A | E35: Innovaccer | F35: Although no directly relevant investments - still cloud based - potential to scale internationally as they specifally mention they partner with founders in India and the US who want to scale | G35: https://www.steadview.com/ | J35: Puneet Kumar | K35: Managing Director | L35: pkumar@steadview.com | M35: https://www.linkedin.com/in/puneetkumarm/
A36: =A35+1 -> 32 | B36: Avataar Ventures | C36: India | D36: N/A | E36: Safe Securities | F36: Although seems to be for early growth ventures (VCs), potential to invest due to relevant prior investments | G36: https://www.avataar.vc/ | J36: Arjun Vikas | K36: Director | L36: arjun@avataar.vc | M36: https://www.linkedin.com/in/arjun-vikas-84118849/
A37: =A36+1 -> 33 | B37: Affirma Capital | C37: Singapore | D37: N/A / mid market | E37: Metanet Group | F37: Global footprint, with offices in India; relevant investments | G37: https://affirmacapital.com/ | J37: Ivo Philipps | K37: COO/Founding Partner | L37: ivo.philipps@affirmacapital.com | M37: https://www.linkedin.com/in/ivo-philipps-5a74244/
A38: =A37+1 -> 34 | B38: Investcorp | C38: Bahrain | D38: N/A/mid market | E38: Calligo | F38: Global footprint with expertise in America, relevant portfolio companies and offices in India | G38: https://www.investcorp.com/ | J38: Timotheus Osnabrug | K38: Investment Partner | L38: tosnabrug@investcorp.com | M38: https://www.linkedin.com/in/timotheus-osnabrug-786b7a65/
A39: =A38+1 -> 35 | B39: BGF | C39: UK | D39: N/A / mid market | E39: Adept4plc | F39: Global footprint with expertise in America, relevant portfolio companies | G39: https://www.bgf.co.uk/ | J39: Pinesh Mehta | K39: Partner | L39: pinesh.mehta@bgf.co.uk | M39: https://www.linkedin.com/in/pinesh-mehta-29448a14/
A40: =A39+1 -> 36 | B40: Iverness Graham | C40: USA | D40: $40m-$80m | E40: Corsica Technologies | F40: From precedent transactions | G40: https://www.invernessgraham.com/ | J40: Steve Wood | K40: Founder | L40: swood@invernessgraham.com | M40: https://www.linkedin.com/in/steve-wood-33b1ab16/
A41: =A40+1 -> 37 | B41: Court Square | C41: USA | D41: $75m-350m equity | E41: Tredence, Thrive | F41: From precedent transactions | G41: https://www.courtsquare.com/ | J41: Michael Delaney | K41: Managing Partner | L41: mdelaney@courtsquare.com | M41: https://www.linkedin.com/in/michael-delaney-9b185116/
A42: =A41+1 -> 38 | B42: Transom Capital | C42: USA | D42: N/A | E42: Secure-Serv | F42: From precedent transactions | G42: https://transomcap.com/ | J42: Steve Kim | K42: Managing Director | L42: skim@transomcap.com | M42: https://www.linkedin.com/in/steve-kim-4194b29/
A43: =A42+1 -> 39 | B43: Runtide Capital | C43: USA | D43: $15m-$35m investments but can do larger | E43: ATSG | F43: From precedent transactions | G43: https://www.runtidecapital.com/ | J43: Robert Manning | K43: Managing Partner | L43: rmanning@runtidecapital.com | M43: https://www.linkedin.com/in/robert-manning-268203/
A44: =A43+1 -> 40 | B44: Prospect Partners | C44: USA | D44: $15m-$100m revenue, $3m-$10m EBITDA | E44: Entech US | F44: From precedent transactions, mentions should be US located | G44: https://prospect-partners.com/ | J44: Erik Maurer | K44: Partner | L44: emaurer@prospect-partners.com | M44: https://www.linkedin.com/in/erikmaurer/
A45: =A44+1 -> 41 | B45: L Squared Capital | C45: USA | D45: $15m-$100m revenue, $3m-$25m EBITDA | E45: Netrio | F45: From related precedent transactions, mentions should be US located | G45: https://www.lsquaredcap.com/ | J45: Adam Kimura | K45: Managing Partner | L45: akimura@lsquaredcap.com | M45: https://www.linkedin.com/in/adam-kimura-28319011/
A46: =A45+1 -> 42 | B46: Perpetual Capital Partners | C46: USA | D46: Upto $250m investments | E46: Novatech | F46: From related precedent transactions, mentions should be US located | G46: https://perpetualcapitalpartners.com/ | J46: Not found
A47: =A46+1 -> 43 | B47: Prarie Capital | C47: USA | D47: N/A / mid market | E47: Blue Alliance IT | F47: From related precedent transactions, mentions should be US located | G47: https://www.prairie-capital.com/ | J47: C. Bryan Daniels | K47: Founding Partner | L47: bdaniels@prairie-capital.com | M47: https://www.linkedin.com/in/c-bryan-daniels-841245127/
A48: =A47+1 -> 44 | B48: The Stephens Group | C48: USA | D48: $5m-$20m revenue, $5m-$30m EBITDA | E48: Armor | F48: From related precedent transactions, mentions should be US located | G48: https://www.stephensgroup.com/ | J48: Jack Nadal | K48: Managing Director | L48: jnadal@stephensgroup.com | M48: https://www.linkedin.com/in/jack-nadal-7157b8a/
A49: =A48+1 -> 45 | B49: Oval Partners | C49: USA | D49: $10m EBITDA | E49: New Charter Technologies | F49: From related precedent transactions, mentions should be US located | G49: https://www.ovalpartners.com/ | J49: John Knoll | K49: Co-Founder | L49: john@ovalpartners.com | M49: https://www.linkedin.com/in/john-knoll-18b0ba1/
A50: =A49+1 -> 46 | B50: Atlantic Street Capital | C50: USA | D50: $15-$75m investments | E50: Cyberguard Compliance | F50: From related precedent transactions, mentions should be US/Canada located | G50: https://www.atlanticstreetcapital.com/ | J50: Baabur Khondker | K50: CCO/CFO/COO | L50: baabur@atlanticstreetcapital.com | M50: https://www.linkedin.com/in/baabur-khondker-3616a75/
A51: =A50+1 -> 47 | B51: Seaport Capital | C51: USA | D51: $10m-$40m investments | E51: Atmosera | F51: From related precedent transactions | G51: https://www.seaportcapital.com/ | J51: Jim Collis | K51: Partner | L51: jim@seaportcapital.com | M51: https://www.linkedin.com/in/jim-collis/
A52: =A51+1 -> 48 | B52: Northwest Equity Partners | C52: USA | D52: $70m-$175m investments | E52: Coretelligent | F52: From related precedent transactions, mentions should be US located | G52: https://nep.com/ | J52: Adam Garcia Eveloff | K52: Partner | L52: aeveloff@nep.com | M52: https://www.linkedin.com/in/adam-garcia-eveloff-a28b5511/
A53: =A52+1 -> 49 | B53: VSS Capital Partners | C53: USA | D53: $3m-$15m EBITDA | E53: Centroid | F53: From related precedent transactions | G53: https://www.vss.com/ | J53: Jeffrey Stevenson | K53: Managing Partner | L53: stevensonj@vss.com | M53: https://www.linkedin.com/in/jeffrey-stevenson-8914318/
A54: =A53+1 -> 50 | B54: Trinity Hunt Partners | C54: USA | D54: $15m-$70m investments | E54: Dataprise | F54: From related precedent transactions | G54: https://www.trinityhunt.com/ | J54: Blake Apel | K54: Managing Partner | L54: bapel@trinityhunt.com | M54: https://www.linkedin.com/in/blake-apel-01855232/
A55: =A54+1 -> 51 | B55: SNH Capital Partners | C55: USA | D55: Upto $75m EBITDA | E55: Five Nines | F55: From related precedent transactions | G55: https://www.snhcapitalpartners.com/ | J55: Reddy Karri | K55: Sr. Operating Partner | L55: rkarri@snhcap.com | M55: https://www.linkedin.com/in/reddykarri/
A56: =A55+1 -> 52 | B56: HCAP Partners | C56: USA | D56: $5m-$35m investments | E56: Lumify | F56: From related precedent transactions | G56: https://www.hcap.com/ | J56: Frank Mora | K56: Partner | L56: frank@hcap.com | M56: https://www.linkedin.com/in/frank-mora-53115bb/
A57: =A56+1 -> 53 | B57: Great Hill Partners | C57: USA | D57: $100m-$750m | E57: Symmetry | F57: From related precedent transactions | G57: https://www.greathillpartners.com/ | J57: Atle Skalleberg | K57: Growth Partner | L57: askalleberg@greathillpartners.com | M57: https://www.linkedin.com/in/skalleberg/
A58: =A57+1 -> 54 | B58: Abry Partners | C58: USA | D58: N/A / mid market | E58: Claranet | F58: From related precedent transactions, invests cross-border | G58: https://abry.com/ | J58: Steve Zammit | K58: Partner | L58: szammit@abry.com | M58: https://www.linkedin.com/in/steve-zammit-a22189/
... A63: =A62+1 -> 59 | B63: Arlington Capital Partners | C63: USA | D63: N/A | E63: SignalTree Solutions | F63: From related precedent transactions | G63: https://arlingtoncap.com/ | J63: Ben Ramundo | K63: Managing Director | L63: bramundo@arlingtoncap.com | M63: https://www.linkedin.com/in/benjaminramundo89/
A64: =A63+1 -> 60 | B64: Stonecourt Capital | C64: USA | D64: N/A | E64: 365 Data Centres | F64: From related precedent transactions | G64: https://www.stonecourtlp.com/
A65: =A64+1 -> 61 | B65: Fulcrum IT Partners | C65: Canada | D65: N/A | E65: Fortress Security Risk Management | F65: From related precedent transactions | G65: https://www.fulcrumitp.com/
A66: =A65+1 -> 62 | B66: La Maison Partners | C66: France | G66: https://www.lamaisonpartners.fr/en/
